{
  "records": {
    "expiryDates": [
      "31-Jul-2025"
    ],
    "data": [
      {
        "strikePrice": 460,
        "expiryDate": "31-Jul-2025",
        "CE": {
          "strikePrice": 460,
          "expiryDate": "31-Jul-2025",
          "underlying": "CHAMBLFERT",
          "identifier": "OPTSTKCHAMBLFERT31-07-2025CE460.00",
          "openInterest": 0,
          "changeinOpenInterest": 0,
          "pchangeinOpenInterest": 0,
          "totalTradedVolume": 0,
          "impliedVolatility": 0,
          "lastPrice": 0,
          "change": 0,
          "pChange": 0,
          "totalBuyQuantity": 75050,
          "totalSellQuantity": 75050,
          "bidQty": 3800,
          "bidprice": 95,
          "askQty": 3800,
          "askPrice": 99.1,
          "underlyingValue": 555.25
        },
        "PE": {
          "strikePrice": 460,
          "expiryDate": "31-Jul-2025",
          "underlying": "CHAMBLFERT",
          "identifier": "OPTSTKCHAMBLFERT31-07-2025PE460.00",
          "openInterest": 41,
          "changeinOpenInterest": 0,
          "pchangeinOpenInterest": 0,
          "totalTradedVolume": 0,
          "impliedVolatility": 0,
          "lastPrice": 0.25,
          "change": 0,
          "pChange": 0,
          "totalBuyQuantity": 49400,
          "totalSellQuantity": 76950,
          "bidQty": 2850,
          "bidprice": 0.1,
          "askQty": 950,
          "askPrice": 0.8,
          "underlyingValue": 555.25
        }
      },
      {
        "strikePrice": 480,
        "expiryDate": "31-Jul-2025",
        "CE": {
          "strikePrice": 480,
          "expiryDate": "31-Jul-2025",
          "underlying": "CHAMBLFERT",
          "identifier": "OPTSTKCHAMBLFERT31-07-2025CE480.00",
          "openInterest": 6,
          "changeinOpenInterest": 0,
          "pchangeinOpenInterest": 0,
          "totalTradedVolume": 0,
          "impliedVolatility": 0,
          "lastPrice": 75,
          "change": 0,
          "pChange": 0,
          "totalBuyQuantity": 75050,
          "totalSellQuantity": 69350,
          "bidQty": 4750,
          "bidprice": 75.15,
          "askQty": 3800,
          "askPrice": 82.5,
          "underlyingValue": 555.25
        },
        "PE": {
          "strikePrice": 480,
          "expiryDate": "31-Jul-2025",
          "underlying": "CHAMBLFERT",
          "identifier": "OPTSTKCHAMBLFERT31-07-2025PE480.00",
          "openInterest": 83,
          "changeinOpenInterest": 0,
          "pchangeinOpenInterest": 0,
          "totalTradedVolume": 0,
          "impliedVolatility": 0,
          "lastPrice": 0.4,
          "change": 0,
          "pChange": 0,
          "totalBuyQuantity": 50350,
          "totalSellQuantity": 122550,
          "bidQty": 950,
          "bidprice": 0.2,
          "askQty": 3800,
          "askPrice": 3.4,
          "underlyingValue": 555.25
        }
      },
      {
        "strikePrice": 490,
        "expiryDate": "31-Jul-2025",
        "PE": {
          "strikePrice": 490,
          "expiryDate": "31-Jul-2025",
          "underlying": "CHAMBLFERT",
          "identifier": "OPTSTKCHAMBLFERT31-07-2025PE490.00",
          "openInterest": 14,
          "changeinOpenInterest": 0,
          "pchangeinOpenInterest": 0,
          "totalTradedVolume": 0,
          "impliedVolatility": 0,
          "lastPrice": 0.55,
          "change": 0,
          "pChange": 0,
          "totalBuyQuantity": 48450,
          "totalSellQuantity": 122550,
          "bidQty": 45600,
          "bidprice": 0.2,
          "askQty": 47500,
          "askPrice": 2.5,
          "underlyingValue": 555.25
        },
        "CE": {
          "strikePrice": 490,
          "expiryDate": "31-Jul-2025",
          "underlying": "CHAMBLFERT",
          "identifier": "OPTSTKCHAMBLFERT31-07-2025CE490.00",
          "openInterest": 0,
          "changeinOpenInterest": 0,
          "pchangeinOpenInterest": 0,
          "totalTradedVolume": 0,
          "impliedVolatility": 0,
          "lastPrice": 0,
          "change": 0,
          "pChange": 0,
          "totalBuyQuantity": 75050,
          "totalSellQuantity": 71250,
          "bidQty": 9500,
          "bidprice": 65.4,
          "askQty": 9500,
          "askPrice": 71.7,
          "underlyingValue": 555.25
        }
      },
      {
        "strikePrice": 500,
        "expiryDate": "31-Jul-2025",
        "CE": {
          "strikePrice": 500,
          "expiryDate": "31-Jul-2025",
          "underlying": "CHAMBLFERT",
          "identifier": "OPTSTKCHAMBLFERT31-07-2025CE500.00",
          "openInterest": 21,
          "changeinOpenInterest": 1,
          "pchangeinOpenInterest": 5,
          "totalTradedVolume": 3,
          "impliedVolatility": 37.5,
          "lastPrice": 58.35,
          "change": -0.75,
          "pChange": -1.2690355329949239,
          "totalBuyQuantity": 80750,
          "totalSellQuantity": 81700,
          "bidQty": 950,
          "bidprice": 57.35,
          "askQty": 950,
          "askPrice": 58.95,
          "underlyingValue": 555.25
        },
        "PE": {
          "strikePrice": 500,
          "expiryDate": "31-Jul-2025",
          "underlying": "CHAMBLFERT",
          "identifier": "OPTSTKCHAMBLFERT31-07-2025PE500.00",
          "openInterest": 256,
          "changeinOpenInterest": -4,
          "pchangeinOpenInterest": -1.5384615384615385,
          "totalTradedVolume": 44,
          "impliedVolatility": 34.85,
          "lastPrice": 0.85,
          "change": -0.2500000000000001,
          "pChange": -22.727272727272734,
          "totalBuyQuantity": 124450,
          "totalSellQuantity": 147250,
          "bidQty": 950,
          "bidprice": 0.8,
          "askQty": 950,
          "askPrice": 0.95,
          "underlyingValue": 555.25
        }
      },
      {
        "strikePrice": 510,
        "expiryDate": "31-Jul-2025",
        "CE": {
          "strikePrice": 510,
          "expiryDate": "31-Jul-2025",
          "underlying": "CHAMBLFERT",
          "identifier": "OPTSTKCHAMBLFERT31-07-2025CE510.00",
          "openInterest": 0,
          "changeinOpenInterest": 0,
          "pchangeinOpenInterest": 0,
          "totalTradedVolume": 0,
          "impliedVolatility": 0,
          "lastPrice": 0,
          "change": 0,
          "pChange": 0,
          "totalBuyQuantity": 77900,
          "totalSellQuantity": 77900,
          "bidQty": 4750,
          "bidprice": 46.45,
          "askQty": 3800,
          "askPrice": 50.35,
          "underlyingValue": 555.25
        },
        "PE": {
          "strikePrice": 510,
          "expiryDate": "31-Jul-2025",
          "underlying": "CHAMBLFERT",
          "identifier": "OPTSTKCHAMBLFERT31-07-2025PE510.00",
          "openInterest": 60,
          "changeinOpenInterest": -1,
          "pchangeinOpenInterest": -1.639344262295082,
          "totalTradedVolume": 10,
          "impliedVolatility": 32.81,
          "lastPrice": 1.3,
          "change": -0.34999999999999987,
          "pChange": -21.212121212121204,
          "totalBuyQuantity": 70300,
          "totalSellQuantity": 139650,
          "bidQty": 950,
          "bidprice": 1.25,
          "askQty": 950,
          "askPrice": 1.35,
          "underlyingValue": 555.25
        }
      },
      {
        "strikePrice": 520,
        "expiryDate": "31-Jul-2025",
        "CE": {
          "strikePrice": 520,
          "expiryDate": "31-Jul-2025",
          "underlying": "CHAMBLFERT",
          "identifier": "OPTSTKCHAMBLFERT31-07-2025CE520.00",
          "openInterest": 36,
          "changeinOpenInterest": 0,
          "pchangeinOpenInterest": 0,
          "totalTradedVolume": 0,
          "impliedVolatility": 0,
          "lastPrice": 36.55,
          "change": 0,
          "pChange": 0,
          "totalBuyQuantity": 77900,
          "totalSellQuantity": 77900,
          "bidQty": 4750,
          "bidprice": 37.3,
          "askQty": 2850,
          "askPrice": 41,
          "underlyingValue": 555.25
        },
        "PE": {
          "strikePrice": 520,
          "expiryDate": "31-Jul-2025",
          "underlying": "CHAMBLFERT",
          "identifier": "OPTSTKCHAMBLFERT31-07-2025PE520.00",
          "openInterest": 195,
          "changeinOpenInterest": 4,
          "pchangeinOpenInterest": 2.094240837696335,
          "totalTradedVolume": 115,
          "impliedVolatility": 30.78,
          "lastPrice": 2,
          "change": -0.75,
          "pChange": -27.27272727272727,
          "totalBuyQuantity": 89300,
          "totalSellQuantity": 180500,
          "bidQty": 3800,
          "bidprice": 1.95,
          "askQty": 1900,
          "askPrice": 2.05,
          "underlyingValue": 555.25
        }
      },
      {
        "strikePrice": 530,
        "expiryDate": "31-Jul-2025",
        "PE": {
          "strikePrice": 530,
          "expiryDate": "31-Jul-2025",
          "underlying": "CHAMBLFERT",
          "identifier": "OPTSTKCHAMBLFERT31-07-2025PE530.00",
          "openInterest": 280,
          "changeinOpenInterest": 23,
          "pchangeinOpenInterest": 8.949416342412452,
          "totalTradedVolume": 427,
          "impliedVolatility": 29.31,
          "lastPrice": 3.25,
          "change": -1.2999999999999998,
          "pChange": -28.57142857142857,
          "totalBuyQuantity": 204250,
          "totalSellQuantity": 229900,
          "bidQty": 1900,
          "bidprice": 3.2,
          "askQty": 1900,
          "askPrice": 3.3,
          "underlyingValue": 555.25
        },
        "CE": {
          "strikePrice": 530,
          "expiryDate": "31-Jul-2025",
          "underlying": "CHAMBLFERT",
          "identifier": "OPTSTKCHAMBLFERT31-07-2025CE530.00",
          "openInterest": 60,
          "changeinOpenInterest": 4,
          "pchangeinOpenInterest": 7.142857142857143,
          "totalTradedVolume": 34,
          "impliedVolatility": 31.9,
          "lastPrice": 31.3,
          "change": 4.100000000000001,
          "pChange": 15.07352941176471,
          "totalBuyQuantity": 101650,
          "totalSellQuantity": 114000,
          "bidQty": 950,
          "bidprice": 29.95,
          "askQty": 950,
          "askPrice": 31,
          "underlyingValue": 555.25
        }
      },
      {
        "strikePrice": 540,
        "expiryDate": "31-Jul-2025",
        "CE": {
          "strikePrice": 540,
          "expiryDate": "31-Jul-2025",
          "underlying": "CHAMBLFERT",
          "identifier": "OPTSTKCHAMBLFERT31-07-2025CE540.00",
          "openInterest": 174,
          "changeinOpenInterest": -2,
          "pchangeinOpenInterest": -1.1363636363636365,
          "totalTradedVolume": 88,
          "impliedVolatility": 29.22,
          "lastPrice": 23,
          "change": 2.8000000000000007,
          "pChange": 13.861386138613865,
          "totalBuyQuantity": 125400,
          "totalSellQuantity": 64600,
          "bidQty": 950,
          "bidprice": 21.25,
          "askQty": 950,
          "askPrice": 24.05,
          "underlyingValue": 555.25
        },
        "PE": {
          "strikePrice": 540,
          "expiryDate": "31-Jul-2025",
          "underlying": "CHAMBLFERT",
          "identifier": "OPTSTKCHAMBLFERT31-07-2025PE540.00",
          "openInterest": 499,
          "changeinOpenInterest": -6,
          "pchangeinOpenInterest": -1.188118811881188,
          "totalTradedVolume": 230,
          "impliedVolatility": 28.72,
          "lastPrice": 5.5,
          "change": -1.7000000000000002,
          "pChange": -23.611111111111114,
          "totalBuyQuantity": 189050,
          "totalSellQuantity": 183350,
          "bidQty": 950,
          "bidprice": 5.25,
          "askQty": 950,
          "askPrice": 5.85,
          "underlyingValue": 555.25
        }
      },
      {
        "strikePrice": 550,
        "expiryDate": "31-Jul-2025",
        "CE": {
          "strikePrice": 550,
          "expiryDate": "31-Jul-2025",
          "underlying": "CHAMBLFERT",
          "identifier": "OPTSTKCHAMBLFERT31-07-2025CE550.00",
          "openInterest": 434,
          "changeinOpenInterest": -21,
          "pchangeinOpenInterest": -4.615384615384615,
          "totalTradedVolume": 703,
          "impliedVolatility": 28.12,
          "lastPrice": 16.15,
          "change": 1.6999999999999993,
          "pChange": 11.764705882352937,
          "totalBuyQuantity": 154850,
          "totalSellQuantity": 164350,
          "bidQty": 1900,
          "bidprice": 15.95,
          "askQty": 950,
          "askPrice": 16.25,
          "underlyingValue": 555.25
        },
        "PE": {
          "strikePrice": 550,
          "expiryDate": "31-Jul-2025",
          "underlying": "CHAMBLFERT",
          "identifier": "OPTSTKCHAMBLFERT31-07-2025PE550.00",
          "openInterest": 412,
          "changeinOpenInterest": -27,
          "pchangeinOpenInterest": -6.150341685649202,
          "totalTradedVolume": 347,
          "impliedVolatility": 27.66,
          "lastPrice": 8.6,
          "change": -2.6500000000000004,
          "pChange": -23.555555555555557,
          "totalBuyQuantity": 191900,
          "totalSellQuantity": 179550,
          "bidQty": 950,
          "bidprice": 8.1,
          "askQty": 950,
          "askPrice": 8.95,
          "underlyingValue": 555.25
        }
      },
      {
        "strikePrice": 560,
        "expiryDate": "31-Jul-2025",
        "CE": {
          "strikePrice": 560,
          "expiryDate": "31-Jul-2025",
          "underlying": "CHAMBLFERT",
          "identifier": "OPTSTKCHAMBLFERT31-07-2025CE560.00",
          "openInterest": 1098,
          "changeinOpenInterest": 129,
          "pchangeinOpenInterest": 13.312693498452012,
          "totalTradedVolume": 1575,
          "impliedVolatility": 28.77,
          "lastPrice": 11.25,
          "change": 1.25,
          "pChange": 12.5,
          "totalBuyQuantity": 234650,
          "totalSellQuantity": 285000,
          "bidQty": 1900,
          "bidprice": 11,
          "askQty": 1900,
          "askPrice": 11.25,
          "underlyingValue": 555.25
        },
        "PE": {
          "strikePrice": 560,
          "expiryDate": "31-Jul-2025",
          "underlying": "CHAMBLFERT",
          "identifier": "OPTSTKCHAMBLFERT31-07-2025PE560.00",
          "openInterest": 431,
          "changeinOpenInterest": -10,
          "pchangeinOpenInterest": -2.2675736961451247,
          "totalTradedVolume": 293,
          "impliedVolatility": 28.3,
          "lastPrice": 13.65,
          "change": -2.9999999999999982,
          "pChange": -18.018018018018008,
          "totalBuyQuantity": 200450,
          "totalSellQuantity": 183350,
          "bidQty": 950,
          "bidprice": 13.15,
          "askQty": 950,
          "askPrice": 14.35,
          "underlyingValue": 555.25
        }
      },
      {
        "strikePrice": 570,
        "expiryDate": "31-Jul-2025",
        "CE": {
          "strikePrice": 570,
          "expiryDate": "31-Jul-2025",
          "underlying": "CHAMBLFERT",
          "identifier": "OPTSTKCHAMBLFERT31-07-2025CE570.00",
          "openInterest": 1077,
          "changeinOpenInterest": -23,
          "pchangeinOpenInterest": -2.090909090909091,
          "totalTradedVolume": 550,
          "impliedVolatility": 28.97,
          "lastPrice": 7.4,
          "change": 0.7000000000000002,
          "pChange": 10.447761194029853,
          "totalBuyQuantity": 184300,
          "totalSellQuantity": 318250,
          "bidQty": 3800,
          "bidprice": 7.15,
          "askQty": 1900,
          "askPrice": 7.4,
          "underlyingValue": 555.25
        },
        "PE": {
          "strikePrice": 570,
          "expiryDate": "31-Jul-2025",
          "underlying": "CHAMBLFERT",
          "identifier": "OPTSTKCHAMBLFERT31-07-2025PE570.00",
          "openInterest": 354,
          "changeinOpenInterest": -2,
          "pchangeinOpenInterest": -0.5617977528089888,
          "totalTradedVolume": 24,
          "impliedVolatility": 29.29,
          "lastPrice": 20.1,
          "change": -1.75,
          "pChange": -8.009153318077802,
          "totalBuyQuantity": 116850,
          "totalSellQuantity": 120650,
          "bidQty": 950,
          "bidprice": 18.3,
          "askQty": 950,
          "askPrice": 20.45,
          "underlyingValue": 555.25
        }
      },
      {
        "strikePrice": 580,
        "expiryDate": "31-Jul-2025",
        "PE": {
          "strikePrice": 580,
          "expiryDate": "31-Jul-2025",
          "underlying": "CHAMBLFERT",
          "identifier": "OPTSTKCHAMBLFERT31-07-2025PE580.00",
          "openInterest": 179,
          "changeinOpenInterest": 1,
          "pchangeinOpenInterest": 0.5617977528089888,
          "totalTradedVolume": 24,
          "impliedVolatility": 28.06,
          "lastPrice": 26.8,
          "change": -1.25,
          "pChange": -4.45632798573975,
          "totalBuyQuantity": 101650,
          "totalSellQuantity": 106400,
          "bidQty": 950,
          "bidprice": 25.95,
          "askQty": 950,
          "askPrice": 28.1,
          "underlyingValue": 555.25
        },
        "CE": {
          "strikePrice": 580,
          "expiryDate": "31-Jul-2025",
          "underlying": "CHAMBLFERT",
          "identifier": "OPTSTKCHAMBLFERT31-07-2025CE580.00",
          "openInterest": 846,
          "changeinOpenInterest": -30,
          "pchangeinOpenInterest": -3.4246575342465753,
          "totalTradedVolume": 809,
          "impliedVolatility": 29.45,
          "lastPrice": 4.75,
          "change": 0.20000000000000018,
          "pChange": 4.3956043956043995,
          "totalBuyQuantity": 286900,
          "totalSellQuantity": 307800,
          "bidQty": 3800,
          "bidprice": 4.75,
          "askQty": 1900,
          "askPrice": 4.85,
          "underlyingValue": 555.25
        }
      },
      {
        "strikePrice": 590,
        "expiryDate": "31-Jul-2025",
        "PE": {
          "strikePrice": 590,
          "expiryDate": "31-Jul-2025",
          "underlying": "CHAMBLFERT",
          "identifier": "OPTSTKCHAMBLFERT31-07-2025PE590.00",
          "openInterest": 36,
          "changeinOpenInterest": 0,
          "pchangeinOpenInterest": 0,
          "totalTradedVolume": 0,
          "impliedVolatility": 0,
          "lastPrice": 39,
          "change": 0,
          "pChange": 0,
          "totalBuyQuantity": 33250,
          "totalSellQuantity": 77900,
          "bidQty": 3800,
          "bidprice": 34,
          "askQty": 6650,
          "askPrice": 37.7,
          "underlyingValue": 555.25
        },
        "CE": {
          "strikePrice": 590,
          "expiryDate": "31-Jul-2025",
          "underlying": "CHAMBLFERT",
          "identifier": "OPTSTKCHAMBLFERT31-07-2025CE590.00",
          "openInterest": 322,
          "changeinOpenInterest": 6,
          "pchangeinOpenInterest": 1.8987341772151898,
          "totalTradedVolume": 258,
          "impliedVolatility": 30.81,
          "lastPrice": 3.2,
          "change": 0.050000000000000266,
          "pChange": 1.5873015873015959,
          "totalBuyQuantity": 251750,
          "totalSellQuantity": 196650,
          "bidQty": 950,
          "bidprice": 3.15,
          "askQty": 1900,
          "askPrice": 3.25,
          "underlyingValue": 555.25
        }
      },
      {
        "strikePrice": 600,
        "expiryDate": "31-Jul-2025",
        "CE": {
          "strikePrice": 600,
          "expiryDate": "31-Jul-2025",
          "underlying": "CHAMBLFERT",
          "identifier": "OPTSTKCHAMBLFERT31-07-2025CE600.00",
          "openInterest": 1366,
          "changeinOpenInterest": 18,
          "pchangeinOpenInterest": 1.3353115727002967,
          "totalTradedVolume": 202,
          "impliedVolatility": 32.53,
          "lastPrice": 2.25,
          "change": 0,
          "pChange": 0,
          "totalBuyQuantity": 203300,
          "totalSellQuantity": 250800,
          "bidQty": 3800,
          "bidprice": 2.25,
          "askQty": 8550,
          "askPrice": 2.3,
          "underlyingValue": 555.25
        },
        "PE": {
          "strikePrice": 600,
          "expiryDate": "31-Jul-2025",
          "underlying": "CHAMBLFERT",
          "identifier": "OPTSTKCHAMBLFERT31-07-2025PE600.00",
          "openInterest": 104,
          "changeinOpenInterest": 1,
          "pchangeinOpenInterest": 0.970873786407767,
          "totalTradedVolume": 9,
          "impliedVolatility": 33.37,
          "lastPrice": 44.9,
          "change": -4.800000000000004,
          "pChange": -9.657947686116708,
          "totalBuyQuantity": 98800,
          "totalSellQuantity": 93100,
          "bidQty": 950,
          "bidprice": 44,
          "askQty": 950,
          "askPrice": 45.5,
          "underlyingValue": 555.25
        }
      },
      {
        "strikePrice": 610,
        "expiryDate": "31-Jul-2025",
        "PE": {
          "strikePrice": 610,
          "expiryDate": "31-Jul-2025",
          "underlying": "CHAMBLFERT",
          "identifier": "OPTSTKCHAMBLFERT31-07-2025PE610.00",
          "openInterest": 26,
          "changeinOpenInterest": 0,
          "pchangeinOpenInterest": 0,
          "totalTradedVolume": 0,
          "impliedVolatility": 0,
          "lastPrice": 52,
          "change": 0,
          "pChange": 0,
          "totalBuyQuantity": 94050,
          "totalSellQuantity": 77900,
          "bidQty": 6650,
          "bidprice": 52.25,
          "askQty": 4750,
          "askPrice": 56.15,
          "underlyingValue": 555.25
        },
        "CE": {
          "strikePrice": 610,
          "expiryDate": "31-Jul-2025",
          "underlying": "CHAMBLFERT",
          "identifier": "OPTSTKCHAMBLFERT31-07-2025CE610.00",
          "openInterest": 344,
          "changeinOpenInterest": 15,
          "pchangeinOpenInterest": 4.5592705167173255,
          "totalTradedVolume": 43,
          "impliedVolatility": 33.64,
          "lastPrice": 1.5,
          "change": -0.050000000000000044,
          "pChange": -3.2258064516129057,
          "totalBuyQuantity": 142500,
          "totalSellQuantity": 147250,
          "bidQty": 1900,
          "bidprice": 1.4,
          "askQty": 950,
          "askPrice": 1.6,
          "underlyingValue": 555.25
        }
      },
      {
        "strikePrice": 620,
        "expiryDate": "31-Jul-2025",
        "CE": {
          "strikePrice": 620,
          "expiryDate": "31-Jul-2025",
          "underlying": "CHAMBLFERT",
          "identifier": "OPTSTKCHAMBLFERT31-07-2025CE620.00",
          "openInterest": 296,
          "changeinOpenInterest": -15,
          "pchangeinOpenInterest": -4.823151125401929,
          "totalTradedVolume": 50,
          "impliedVolatility": 36.46,
          "lastPrice": 1.25,
          "change": 0,
          "pChange": 0,
          "totalBuyQuantity": 122550,
          "totalSellQuantity": 154850,
          "bidQty": 950,
          "bidprice": 1.05,
          "askQty": 950,
          "askPrice": 1.15,
          "underlyingValue": 555.25
        },
        "PE": {
          "strikePrice": 620,
          "expiryDate": "31-Jul-2025",
          "underlying": "CHAMBLFERT",
          "identifier": "OPTSTKCHAMBLFERT31-07-2025PE620.00",
          "openInterest": 28,
          "changeinOpenInterest": -2,
          "pchangeinOpenInterest": -6.666666666666667,
          "totalTradedVolume": 2,
          "impliedVolatility": 48.15,
          "lastPrice": 65.95,
          "change": -6.349999999999994,
          "pChange": -8.782849239280766,
          "totalBuyQuantity": 77900,
          "totalSellQuantity": 76000,
          "bidQty": 950,
          "bidprice": 62.7,
          "askQty": 950,
          "askPrice": 64.65,
          "underlyingValue": 555.25
        }
      },
      {
        "strikePrice": 630,
        "expiryDate": "31-Jul-2025",
        "CE": {
          "strikePrice": 630,
          "expiryDate": "31-Jul-2025",
          "underlying": "CHAMBLFERT",
          "identifier": "OPTSTKCHAMBLFERT31-07-2025CE630.00",
          "openInterest": 184,
          "changeinOpenInterest": 0,
          "pchangeinOpenInterest": 0,
          "totalTradedVolume": 1,
          "impliedVolatility": 38.69,
          "lastPrice": 1,
          "change": 0.050000000000000044,
          "pChange": 5.263157894736848,
          "totalBuyQuantity": 124450,
          "totalSellQuantity": 128250,
          "bidQty": 950,
          "bidprice": 0.7,
          "askQty": 950,
          "askPrice": 1,
          "underlyingValue": 555.25
        },
        "PE": {
          "strikePrice": 630,
          "expiryDate": "31-Jul-2025",
          "underlying": "CHAMBLFERT",
          "identifier": "OPTSTKCHAMBLFERT31-07-2025PE630.00",
          "openInterest": 15,
          "changeinOpenInterest": 0,
          "pchangeinOpenInterest": 0,
          "totalTradedVolume": 0,
          "impliedVolatility": 0,
          "lastPrice": 76.8,
          "change": 0,
          "pChange": 0,
          "totalBuyQuantity": 75050,
          "totalSellQuantity": 75050,
          "bidQty": 3800,
          "bidprice": 71.55,
          "askQty": 3800,
          "askPrice": 75.4,
          "underlyingValue": 555.25
        }
      },
      {
        "strikePrice": 640,
        "expiryDate": "31-Jul-2025",
        "CE": {
          "strikePrice": 640,
          "expiryDate": "31-Jul-2025",
          "underlying": "CHAMBLFERT",
          "identifier": "OPTSTKCHAMBLFERT31-07-2025CE640.00",
          "openInterest": 248,
          "changeinOpenInterest": 5,
          "pchangeinOpenInterest": 2.05761316872428,
          "totalTradedVolume": 13,
          "impliedVolatility": 39.72,
          "lastPrice": 0.7,
          "change": 0.04999999999999993,
          "pChange": 7.692307692307682,
          "totalBuyQuantity": 124450,
          "totalSellQuantity": 155800,
          "bidQty": 1900,
          "bidprice": 0.55,
          "askQty": 950,
          "askPrice": 0.7,
          "underlyingValue": 555.25
        },
        "PE": {
          "strikePrice": 640,
          "expiryDate": "31-Jul-2025",
          "underlying": "CHAMBLFERT",
          "identifier": "OPTSTKCHAMBLFERT31-07-2025PE640.00",
          "openInterest": 49,
          "changeinOpenInterest": 0,
          "pchangeinOpenInterest": 0,
          "totalTradedVolume": 0,
          "impliedVolatility": 0,
          "lastPrice": 81.95,
          "change": 0,
          "pChange": 0,
          "totalBuyQuantity": 86450,
          "totalSellQuantity": 86450,
          "bidQty": 3800,
          "bidprice": 81.15,
          "askQty": 4750,
          "askPrice": 85.3,
          "underlyingValue": 555.25
        }
      }
    ],
    "timestamp": "17-Jul-2025 15:30:00",
    "underlyingValue": 555.25,
    "strikePrices": [
      460,
      480,
      490,
      500,
      510,
      520,
      530,
      540,
      550,
      560,
      570,
      580,
      590,
      600,
      610,
      620,
      630,
      640
    ]
  },
  "filtered": {
    "data": [
      {
        "strikePrice": 460,
        "expiryDate": "31-Jul-2025",
        "CE": {
          "strikePrice": 460,
          "expiryDate": "31-Jul-2025",
          "underlying": "CHAMBLFERT",
          "identifier": "OPTSTKCHAMBLFERT31-07-2025CE460.00",
          "openInterest": 0,
          "changeinOpenInterest": 0,
          "pchangeinOpenInterest": 0,
          "totalTradedVolume": 0,
          "impliedVolatility": 0,
          "lastPrice": 0,
          "change": 0,
          "pChange": 0,
          "totalBuyQuantity": 75050,
          "totalSellQuantity": 75050,
          "bidQty": 3800,
          "bidprice": 95,
          "askQty": 3800,
          "askPrice": 99.1,
          "underlyingValue": 555.25
        },
        "PE": {
          "strikePrice": 460,
          "expiryDate": "31-Jul-2025",
          "underlying": "CHAMBLFERT",
          "identifier": "OPTSTKCHAMBLFERT31-07-2025PE460.00",
          "openInterest": 41,
          "changeinOpenInterest": 0,
          "pchangeinOpenInterest": 0,
          "totalTradedVolume": 0,
          "impliedVolatility": 0,
          "lastPrice": 0.25,
          "change": 0,
          "pChange": 0,
          "totalBuyQuantity": 49400,
          "totalSellQuantity": 76950,
          "bidQty": 2850,
          "bidprice": 0.1,
          "askQty": 950,
          "askPrice": 0.8,
          "underlyingValue": 555.25
        }
      },
      {
        "strikePrice": 480,
        "expiryDate": "31-Jul-2025",
        "CE": {
          "strikePrice": 480,
          "expiryDate": "31-Jul-2025",
          "underlying": "CHAMBLFERT",
          "identifier": "OPTSTKCHAMBLFERT31-07-2025CE480.00",
          "openInterest": 6,
          "changeinOpenInterest": 0,
          "pchangeinOpenInterest": 0,
          "totalTradedVolume": 0,
          "impliedVolatility": 0,
          "lastPrice": 75,
          "change": 0,
          "pChange": 0,
          "totalBuyQuantity": 75050,
          "totalSellQuantity": 69350,
          "bidQty": 4750,
          "bidprice": 75.15,
          "askQty": 3800,
          "askPrice": 82.5,
          "underlyingValue": 555.25
        },
        "PE": {
          "strikePrice": 480,
          "expiryDate": "31-Jul-2025",
          "underlying": "CHAMBLFERT",
          "identifier": "OPTSTKCHAMBLFERT31-07-2025PE480.00",
          "openInterest": 83,
          "changeinOpenInterest": 0,
          "pchangeinOpenInterest": 0,
          "totalTradedVolume": 0,
          "impliedVolatility": 0,
          "lastPrice": 0.4,
          "change": 0,
          "pChange": 0,
          "totalBuyQuantity": 50350,
          "totalSellQuantity": 122550,
          "bidQty": 950,
          "bidprice": 0.2,
          "askQty": 3800,
          "askPrice": 3.4,
          "underlyingValue": 555.25
        }
      },
      {
        "strikePrice": 490,
        "expiryDate": "31-Jul-2025",
        "PE": {
          "strikePrice": 490,
          "expiryDate": "31-Jul-2025",
          "underlying": "CHAMBLFERT",
          "identifier": "OPTSTKCHAMBLFERT31-07-2025PE490.00",
          "openInterest": 14,
          "changeinOpenInterest": 0,
          "pchangeinOpenInterest": 0,
          "totalTradedVolume": 0,
          "impliedVolatility": 0,
          "lastPrice": 0.55,
          "change": 0,
          "pChange": 0,
          "totalBuyQuantity": 48450,
          "totalSellQuantity": 122550,
          "bidQty": 45600,
          "bidprice": 0.2,
          "askQty": 47500,
          "askPrice": 2.5,
          "underlyingValue": 555.25
        },
        "CE": {
          "strikePrice": 490,
          "expiryDate": "31-Jul-2025",
          "underlying": "CHAMBLFERT",
          "identifier": "OPTSTKCHAMBLFERT31-07-2025CE490.00",
          "openInterest": 0,
          "changeinOpenInterest": 0,
          "pchangeinOpenInterest": 0,
          "totalTradedVolume": 0,
          "impliedVolatility": 0,
          "lastPrice": 0,
          "change": 0,
          "pChange": 0,
          "totalBuyQuantity": 75050,
          "totalSellQuantity": 71250,
          "bidQty": 9500,
          "bidprice": 65.4,
          "askQty": 9500,
          "askPrice": 71.7,
          "underlyingValue": 555.25
        }
      },
      {
        "strikePrice": 500,
        "expiryDate": "31-Jul-2025",
        "CE": {
          "strikePrice": 500,
          "expiryDate": "31-Jul-2025",
          "underlying": "CHAMBLFERT",
          "identifier": "OPTSTKCHAMBLFERT31-07-2025CE500.00",
          "openInterest": 21,
          "changeinOpenInterest": 1,
          "pchangeinOpenInterest": 5,
          "totalTradedVolume": 3,
          "impliedVolatility": 37.5,
          "lastPrice": 58.35,
          "change": -0.75,
          "pChange": -1.2690355329949239,
          "totalBuyQuantity": 80750,
          "totalSellQuantity": 81700,
          "bidQty": 950,
          "bidprice": 57.35,
          "askQty": 950,
          "askPrice": 58.95,
          "underlyingValue": 555.25
        },
        "PE": {
          "strikePrice": 500,
          "expiryDate": "31-Jul-2025",
          "underlying": "CHAMBLFERT",
          "identifier": "OPTSTKCHAMBLFERT31-07-2025PE500.00",
          "openInterest": 256,
          "changeinOpenInterest": -4,
          "pchangeinOpenInterest": -1.5384615384615385,
          "totalTradedVolume": 44,
          "impliedVolatility": 34.85,
          "lastPrice": 0.85,
          "change": -0.2500000000000001,
          "pChange": -22.727272727272734,
          "totalBuyQuantity": 124450,
          "totalSellQuantity": 147250,
          "bidQty": 950,
          "bidprice": 0.8,
          "askQty": 950,
          "askPrice": 0.95,
          "underlyingValue": 555.25
        }
      },
      {
        "strikePrice": 510,
        "expiryDate": "31-Jul-2025",
        "CE": {
          "strikePrice": 510,
          "expiryDate": "31-Jul-2025",
          "underlying": "CHAMBLFERT",
          "identifier": "OPTSTKCHAMBLFERT31-07-2025CE510.00",
          "openInterest": 0,
          "changeinOpenInterest": 0,
          "pchangeinOpenInterest": 0,
          "totalTradedVolume": 0,
          "impliedVolatility": 0,
          "lastPrice": 0,
          "change": 0,
          "pChange": 0,
          "totalBuyQuantity": 77900,
          "totalSellQuantity": 77900,
          "bidQty": 4750,
          "bidprice": 46.45,
          "askQty": 3800,
          "askPrice": 50.35,
          "underlyingValue": 555.25
        },
        "PE": {
          "strikePrice": 510,
          "expiryDate": "31-Jul-2025",
          "underlying": "CHAMBLFERT",
          "identifier": "OPTSTKCHAMBLFERT31-07-2025PE510.00",
          "openInterest": 60,
          "changeinOpenInterest": -1,
          "pchangeinOpenInterest": -1.639344262295082,
          "totalTradedVolume": 10,
          "impliedVolatility": 32.81,
          "lastPrice": 1.3,
          "change": -0.34999999999999987,
          "pChange": -21.212121212121204,
          "totalBuyQuantity": 70300,
          "totalSellQuantity": 139650,
          "bidQty": 950,
          "bidprice": 1.25,
          "askQty": 950,
          "askPrice": 1.35,
          "underlyingValue": 555.25
        }
      },
      {
        "strikePrice": 520,
        "expiryDate": "31-Jul-2025",
        "CE": {
          "strikePrice": 520,
          "expiryDate": "31-Jul-2025",
          "underlying": "CHAMBLFERT",
          "identifier": "OPTSTKCHAMBLFERT31-07-2025CE520.00",
          "openInterest": 36,
          "changeinOpenInterest": 0,
          "pchangeinOpenInterest": 0,
          "totalTradedVolume": 0,
          "impliedVolatility": 0,
          "lastPrice": 36.55,
          "change": 0,
          "pChange": 0,
          "totalBuyQuantity": 77900,
          "totalSellQuantity": 77900,
          "bidQty": 4750,
          "bidprice": 37.3,
          "askQty": 2850,
          "askPrice": 41,
          "underlyingValue": 555.25
        },
        "PE": {
          "strikePrice": 520,
          "expiryDate": "31-Jul-2025",
          "underlying": "CHAMBLFERT",
          "identifier": "OPTSTKCHAMBLFERT31-07-2025PE520.00",
          "openInterest": 195,
          "changeinOpenInterest": 4,
          "pchangeinOpenInterest": 2.094240837696335,
          "totalTradedVolume": 115,
          "impliedVolatility": 30.78,
          "lastPrice": 2,
          "change": -0.75,
          "pChange": -27.27272727272727,
          "totalBuyQuantity": 89300,
          "totalSellQuantity": 180500,
          "bidQty": 3800,
          "bidprice": 1.95,
          "askQty": 1900,
          "askPrice": 2.05,
          "underlyingValue": 555.25
        }
      },
      {
        "strikePrice": 530,
        "expiryDate": "31-Jul-2025",
        "PE": {
          "strikePrice": 530,
          "expiryDate": "31-Jul-2025",
          "underlying": "CHAMBLFERT",
          "identifier": "OPTSTKCHAMBLFERT31-07-2025PE530.00",
          "openInterest": 280,
          "changeinOpenInterest": 23,
          "pchangeinOpenInterest": 8.949416342412452,
          "totalTradedVolume": 427,
          "impliedVolatility": 29.31,
          "lastPrice": 3.25,
          "change": -1.2999999999999998,
          "pChange": -28.57142857142857,
          "totalBuyQuantity": 204250,
          "totalSellQuantity": 229900,
          "bidQty": 1900,
          "bidprice": 3.2,
          "askQty": 1900,
          "askPrice": 3.3,
          "underlyingValue": 555.25
        },
        "CE": {
          "strikePrice": 530,
          "expiryDate": "31-Jul-2025",
          "underlying": "CHAMBLFERT",
          "identifier": "OPTSTKCHAMBLFERT31-07-2025CE530.00",
          "openInterest": 60,
          "changeinOpenInterest": 4,
          "pchangeinOpenInterest": 7.142857142857143,
          "totalTradedVolume": 34,
          "impliedVolatility": 31.9,
          "lastPrice": 31.3,
          "change": 4.100000000000001,
          "pChange": 15.07352941176471,
          "totalBuyQuantity": 101650,
          "totalSellQuantity": 114000,
          "bidQty": 950,
          "bidprice": 29.95,
          "askQty": 950,
          "askPrice": 31,
          "underlyingValue": 555.25
        }
      },
      {
        "strikePrice": 540,
        "expiryDate": "31-Jul-2025",
        "CE": {
          "strikePrice": 540,
          "expiryDate": "31-Jul-2025",
          "underlying": "CHAMBLFERT",
          "identifier": "OPTSTKCHAMBLFERT31-07-2025CE540.00",
          "openInterest": 174,
          "changeinOpenInterest": -2,
          "pchangeinOpenInterest": -1.1363636363636365,
          "totalTradedVolume": 88,
          "impliedVolatility": 29.22,
          "lastPrice": 23,
          "change": 2.8000000000000007,
          "pChange": 13.861386138613865,
          "totalBuyQuantity": 125400,
          "totalSellQuantity": 64600,
          "bidQty": 950,
          "bidprice": 21.25,
          "askQty": 950,
          "askPrice": 24.05,
          "underlyingValue": 555.25
        },
        "PE": {
          "strikePrice": 540,
          "expiryDate": "31-Jul-2025",
          "underlying": "CHAMBLFERT",
          "identifier": "OPTSTKCHAMBLFERT31-07-2025PE540.00",
          "openInterest": 499,
          "changeinOpenInterest": -6,
          "pchangeinOpenInterest": -1.188118811881188,
          "totalTradedVolume": 230,
          "impliedVolatility": 28.72,
          "lastPrice": 5.5,
          "change": -1.7000000000000002,
          "pChange": -23.611111111111114,
          "totalBuyQuantity": 189050,
          "totalSellQuantity": 183350,
          "bidQty": 950,
          "bidprice": 5.25,
          "askQty": 950,
          "askPrice": 5.85,
          "underlyingValue": 555.25
        }
      },
      {
        "strikePrice": 550,
        "expiryDate": "31-Jul-2025",
        "CE": {
          "strikePrice": 550,
          "expiryDate": "31-Jul-2025",
          "underlying": "CHAMBLFERT",
          "identifier": "OPTSTKCHAMBLFERT31-07-2025CE550.00",
          "openInterest": 434,
          "changeinOpenInterest": -21,
          "pchangeinOpenInterest": -4.615384615384615,
          "totalTradedVolume": 703,
          "impliedVolatility": 28.12,
          "lastPrice": 16.15,
          "change": 1.6999999999999993,
          "pChange": 11.764705882352937,
          "totalBuyQuantity": 154850,
          "totalSellQuantity": 164350,
          "bidQty": 1900,
          "bidprice": 15.95,
          "askQty": 950,
          "askPrice": 16.25,
          "underlyingValue": 555.25
        },
        "PE": {
          "strikePrice": 550,
          "expiryDate": "31-Jul-2025",
          "underlying": "CHAMBLFERT",
          "identifier": "OPTSTKCHAMBLFERT31-07-2025PE550.00",
          "openInterest": 412,
          "changeinOpenInterest": -27,
          "pchangeinOpenInterest": -6.150341685649202,
          "totalTradedVolume": 347,
          "impliedVolatility": 27.66,
          "lastPrice": 8.6,
          "change": -2.6500000000000004,
          "pChange": -23.555555555555557,
          "totalBuyQuantity": 191900,
          "totalSellQuantity": 179550,
          "bidQty": 950,
          "bidprice": 8.1,
          "askQty": 950,
          "askPrice": 8.95,
          "underlyingValue": 555.25
        }
      },
      {
        "strikePrice": 560,
        "expiryDate": "31-Jul-2025",
        "CE": {
          "strikePrice": 560,
          "expiryDate": "31-Jul-2025",
          "underlying": "CHAMBLFERT",
          "identifier": "OPTSTKCHAMBLFERT31-07-2025CE560.00",
          "openInterest": 1098,
          "changeinOpenInterest": 129,
          "pchangeinOpenInterest": 13.312693498452012,
          "totalTradedVolume": 1575,
          "impliedVolatility": 28.77,
          "lastPrice": 11.25,
          "change": 1.25,
          "pChange": 12.5,
          "totalBuyQuantity": 234650,
          "totalSellQuantity": 285000,
          "bidQty": 1900,
          "bidprice": 11,
          "askQty": 1900,
          "askPrice": 11.25,
          "underlyingValue": 555.25
        },
        "PE": {
          "strikePrice": 560,
          "expiryDate": "31-Jul-2025",
          "underlying": "CHAMBLFERT",
          "identifier": "OPTSTKCHAMBLFERT31-07-2025PE560.00",
          "openInterest": 431,
          "changeinOpenInterest": -10,
          "pchangeinOpenInterest": -2.2675736961451247,
          "totalTradedVolume": 293,
          "impliedVolatility": 28.3,
          "lastPrice": 13.65,
          "change": -2.9999999999999982,
          "pChange": -18.018018018018008,
          "totalBuyQuantity": 200450,
          "totalSellQuantity": 183350,
          "bidQty": 950,
          "bidprice": 13.15,
          "askQty": 950,
          "askPrice": 14.35,
          "underlyingValue": 555.25
        }
      },
      {
        "strikePrice": 570,
        "expiryDate": "31-Jul-2025",
        "CE": {
          "strikePrice": 570,
          "expiryDate": "31-Jul-2025",
          "underlying": "CHAMBLFERT",
          "identifier": "OPTSTKCHAMBLFERT31-07-2025CE570.00",
          "openInterest": 1077,
          "changeinOpenInterest": -23,
          "pchangeinOpenInterest": -2.090909090909091,
          "totalTradedVolume": 550,
          "impliedVolatility": 28.97,
          "lastPrice": 7.4,
          "change": 0.7000000000000002,
          "pChange": 10.447761194029853,
          "totalBuyQuantity": 184300,
          "totalSellQuantity": 318250,
          "bidQty": 3800,
          "bidprice": 7.15,
          "askQty": 1900,
          "askPrice": 7.4,
          "underlyingValue": 555.25
        },
        "PE": {
          "strikePrice": 570,
          "expiryDate": "31-Jul-2025",
          "underlying": "CHAMBLFERT",
          "identifier": "OPTSTKCHAMBLFERT31-07-2025PE570.00",
          "openInterest": 354,
          "changeinOpenInterest": -2,
          "pchangeinOpenInterest": -0.5617977528089888,
          "totalTradedVolume": 24,
          "impliedVolatility": 29.29,
          "lastPrice": 20.1,
          "change": -1.75,
          "pChange": -8.009153318077802,
          "totalBuyQuantity": 116850,
          "totalSellQuantity": 120650,
          "bidQty": 950,
          "bidprice": 18.3,
          "askQty": 950,
          "askPrice": 20.45,
          "underlyingValue": 555.25
        }
      },
      {
        "strikePrice": 580,
        "expiryDate": "31-Jul-2025",
        "PE": {
          "strikePrice": 580,
          "expiryDate": "31-Jul-2025",
          "underlying": "CHAMBLFERT",
          "identifier": "OPTSTKCHAMBLFERT31-07-2025PE580.00",
          "openInterest": 179,
          "changeinOpenInterest": 1,
          "pchangeinOpenInterest": 0.5617977528089888,
          "totalTradedVolume": 24,
          "impliedVolatility": 28.06,
          "lastPrice": 26.8,
          "change": -1.25,
          "pChange": -4.45632798573975,
          "totalBuyQuantity": 101650,
          "totalSellQuantity": 106400,
          "bidQty": 950,
          "bidprice": 25.95,
          "askQty": 950,
          "askPrice": 28.1,
          "underlyingValue": 555.25
        },
        "CE": {
          "strikePrice": 580,
          "expiryDate": "31-Jul-2025",
          "underlying": "CHAMBLFERT",
          "identifier": "OPTSTKCHAMBLFERT31-07-2025CE580.00",
          "openInterest": 846,
          "changeinOpenInterest": -30,
          "pchangeinOpenInterest": -3.4246575342465753,
          "totalTradedVolume": 809,
          "impliedVolatility": 29.45,
          "lastPrice": 4.75,
          "change": 0.20000000000000018,
          "pChange": 4.3956043956043995,
          "totalBuyQuantity": 286900,
          "totalSellQuantity": 307800,
          "bidQty": 3800,
          "bidprice": 4.75,
          "askQty": 1900,
          "askPrice": 4.85,
          "underlyingValue": 555.25
        }
      },
      {
        "strikePrice": 590,
        "expiryDate": "31-Jul-2025",
        "PE": {
          "strikePrice": 590,
          "expiryDate": "31-Jul-2025",
          "underlying": "CHAMBLFERT",
          "identifier": "OPTSTKCHAMBLFERT31-07-2025PE590.00",
          "openInterest": 36,
          "changeinOpenInterest": 0,
          "pchangeinOpenInterest": 0,
          "totalTradedVolume": 0,
          "impliedVolatility": 0,
          "lastPrice": 39,
          "change": 0,
          "pChange": 0,
          "totalBuyQuantity": 33250,
          "totalSellQuantity": 77900,
          "bidQty": 3800,
          "bidprice": 34,
          "askQty": 6650,
          "askPrice": 37.7,
          "underlyingValue": 555.25
        },
        "CE": {
          "strikePrice": 590,
          "expiryDate": "31-Jul-2025",
          "underlying": "CHAMBLFERT",
          "identifier": "OPTSTKCHAMBLFERT31-07-2025CE590.00",
          "openInterest": 322,
          "changeinOpenInterest": 6,
          "pchangeinOpenInterest": 1.8987341772151898,
          "totalTradedVolume": 258,
          "impliedVolatility": 30.81,
          "lastPrice": 3.2,
          "change": 0.050000000000000266,
          "pChange": 1.5873015873015959,
          "totalBuyQuantity": 251750,
          "totalSellQuantity": 196650,
          "bidQty": 950,
          "bidprice": 3.15,
          "askQty": 1900,
          "askPrice": 3.25,
          "underlyingValue": 555.25
        }
      },
      {
        "strikePrice": 600,
        "expiryDate": "31-Jul-2025",
        "CE": {
          "strikePrice": 600,
          "expiryDate": "31-Jul-2025",
          "underlying": "CHAMBLFERT",
          "identifier": "OPTSTKCHAMBLFERT31-07-2025CE600.00",
          "openInterest": 1366,
          "changeinOpenInterest": 18,
          "pchangeinOpenInterest": 1.3353115727002967,
          "totalTradedVolume": 202,
          "impliedVolatility": 32.53,
          "lastPrice": 2.25,
          "change": 0,
          "pChange": 0,
          "totalBuyQuantity": 203300,
          "totalSellQuantity": 250800,
          "bidQty": 3800,
          "bidprice": 2.25,
          "askQty": 8550,
          "askPrice": 2.3,
          "underlyingValue": 555.25
        },
        "PE": {
          "strikePrice": 600,
          "expiryDate": "31-Jul-2025",
          "underlying": "CHAMBLFERT",
          "identifier": "OPTSTKCHAMBLFERT31-07-2025PE600.00",
          "openInterest": 104,
          "changeinOpenInterest": 1,
          "pchangeinOpenInterest": 0.970873786407767,
          "totalTradedVolume": 9,
          "impliedVolatility": 33.37,
          "lastPrice": 44.9,
          "change": -4.800000000000004,
          "pChange": -9.657947686116708,
          "totalBuyQuantity": 98800,
          "totalSellQuantity": 93100,
          "bidQty": 950,
          "bidprice": 44,
          "askQty": 950,
          "askPrice": 45.5,
          "underlyingValue": 555.25
        }
      },
      {
        "strikePrice": 610,
        "expiryDate": "31-Jul-2025",
        "PE": {
          "strikePrice": 610,
          "expiryDate": "31-Jul-2025",
          "underlying": "CHAMBLFERT",
          "identifier": "OPTSTKCHAMBLFERT31-07-2025PE610.00",
          "openInterest": 26,
          "changeinOpenInterest": 0,
          "pchangeinOpenInterest": 0,
          "totalTradedVolume": 0,
          "impliedVolatility": 0,
          "lastPrice": 52,
          "change": 0,
          "pChange": 0,
          "totalBuyQuantity": 94050,
          "totalSellQuantity": 77900,
          "bidQty": 6650,
          "bidprice": 52.25,
          "askQty": 4750,
          "askPrice": 56.15,
          "underlyingValue": 555.25
        },
        "CE": {
          "strikePrice": 610,
          "expiryDate": "31-Jul-2025",
          "underlying": "CHAMBLFERT",
          "identifier": "OPTSTKCHAMBLFERT31-07-2025CE610.00",
          "openInterest": 344,
          "changeinOpenInterest": 15,
          "pchangeinOpenInterest": 4.5592705167173255,
          "totalTradedVolume": 43,
          "impliedVolatility": 33.64,
          "lastPrice": 1.5,
          "change": -0.050000000000000044,
          "pChange": -3.2258064516129057,
          "totalBuyQuantity": 142500,
          "totalSellQuantity": 147250,
          "bidQty": 1900,
          "bidprice": 1.4,
          "askQty": 950,
          "askPrice": 1.6,
          "underlyingValue": 555.25
        }
      },
      {
        "strikePrice": 620,
        "expiryDate": "31-Jul-2025",
        "CE": {
          "strikePrice": 620,
          "expiryDate": "31-Jul-2025",
          "underlying": "CHAMBLFERT",
          "identifier": "OPTSTKCHAMBLFERT31-07-2025CE620.00",
          "openInterest": 296,
          "changeinOpenInterest": -15,
          "pchangeinOpenInterest": -4.823151125401929,
          "totalTradedVolume": 50,
          "impliedVolatility": 36.46,
          "lastPrice": 1.25,
          "change": 0,
          "pChange": 0,
          "totalBuyQuantity": 122550,
          "totalSellQuantity": 154850,
          "bidQty": 950,
          "bidprice": 1.05,
          "askQty": 950,
          "askPrice": 1.15,
          "underlyingValue": 555.25
        },
        "PE": {
          "strikePrice": 620,
          "expiryDate": "31-Jul-2025",
          "underlying": "CHAMBLFERT",
          "identifier": "OPTSTKCHAMBLFERT31-07-2025PE620.00",
          "openInterest": 28,
          "changeinOpenInterest": -2,
          "pchangeinOpenInterest": -6.666666666666667,
          "totalTradedVolume": 2,
          "impliedVolatility": 48.15,
          "lastPrice": 65.95,
          "change": -6.349999999999994,
          "pChange": -8.782849239280766,
          "totalBuyQuantity": 77900,
          "totalSellQuantity": 76000,
          "bidQty": 950,
          "bidprice": 62.7,
          "askQty": 950,
          "askPrice": 64.65,
          "underlyingValue": 555.25
        }
      },
      {
        "strikePrice": 630,
        "expiryDate": "31-Jul-2025",
        "CE": {
          "strikePrice": 630,
          "expiryDate": "31-Jul-2025",
          "underlying": "CHAMBLFERT",
          "identifier": "OPTSTKCHAMBLFERT31-07-2025CE630.00",
          "openInterest": 184,
          "changeinOpenInterest": 0,
          "pchangeinOpenInterest": 0,
          "totalTradedVolume": 1,
          "impliedVolatility": 38.69,
          "lastPrice": 1,
          "change": 0.050000000000000044,
          "pChange": 5.263157894736848,
          "totalBuyQuantity": 124450,
          "totalSellQuantity": 128250,
          "bidQty": 950,
          "bidprice": 0.7,
          "askQty": 950,
          "askPrice": 1,
          "underlyingValue": 555.25
        },
        "PE": {
          "strikePrice": 630,
          "expiryDate": "31-Jul-2025",
          "underlying": "CHAMBLFERT",
          "identifier": "OPTSTKCHAMBLFERT31-07-2025PE630.00",
          "openInterest": 15,
          "changeinOpenInterest": 0,
          "pchangeinOpenInterest": 0,
          "totalTradedVolume": 0,
          "impliedVolatility": 0,
          "lastPrice": 76.8,
          "change": 0,
          "pChange": 0,
          "totalBuyQuantity": 75050,
          "totalSellQuantity": 75050,
          "bidQty": 3800,
          "bidprice": 71.55,
          "askQty": 3800,
          "askPrice": 75.4,
          "underlyingValue": 555.25
        }
      },
      {
        "strikePrice": 640,
        "expiryDate": "31-Jul-2025",
        "CE": {
          "strikePrice": 640,
          "expiryDate": "31-Jul-2025",
          "underlying": "CHAMBLFERT",
          "identifier": "OPTSTKCHAMBLFERT31-07-2025CE640.00",
          "openInterest": 248,
          "changeinOpenInterest": 5,
          "pchangeinOpenInterest": 2.05761316872428,
          "totalTradedVolume": 13,
          "impliedVolatility": 39.72,
          "lastPrice": 0.7,
          "change": 0.04999999999999993,
          "pChange": 7.692307692307682,
          "totalBuyQuantity": 124450,
          "totalSellQuantity": 155800,
          "bidQty": 1900,
          "bidprice": 0.55,
          "askQty": 950,
          "askPrice": 0.7,
          "underlyingValue": 555.25
        },
        "PE": {
          "strikePrice": 640,
          "expiryDate": "31-Jul-2025",
          "underlying": "CHAMBLFERT",
          "identifier": "OPTSTKCHAMBLFERT31-07-2025PE640.00",
          "openInterest": 49,
          "changeinOpenInterest": 0,
          "pchangeinOpenInterest": 0,
          "totalTradedVolume": 0,
          "impliedVolatility": 0,
          "lastPrice": 81.95,
          "change": 0,
          "pChange": 0,
          "totalBuyQuantity": 86450,
          "totalSellQuantity": 86450,
          "bidQty": 3800,
          "bidprice": 81.15,
          "askQty": 4750,
          "askPrice": 85.3,
          "underlyingValue": 555.25
        }
      }
    ],
    "CE": {
      "totOI": 6512,
      "totVol": 4329
    },
    "PE": {
      "totOI": 3062,
      "totVol": 1525
    }
  }
}