{
  "records": {
    "expiryDates": [
      "31-Jul-2025",
      "28-Aug-2025"
    ],
    "data": [
      {
        "strikePrice": 3600,
        "expiryDate": "31-Jul-2025",
        "CE": {
          "strikePrice": 3600,
          "expiryDate": "31-Jul-2025",
          "underlying": "SUPREMEIND",
          "identifier": "OPTSTKSUPREMEIND31-07-2025CE3600.00",
          "openInterest": 0,
          "changeinOpenInterest": 0,
          "pchangeinOpenInterest": 0,
          "totalTradedVolume": 0,
          "impliedVolatility": 0,
          "lastPrice": 0,
          "change": 0,
          "pChange": 0,
          "totalBuyQuantity": 10325,
          "totalSellQuantity": 9450,
          "bidQty": 875,
          "bidprice": 640.8,
          "askQty": 1750,
          "askPrice": 687.6,
          "underlyingValue": 4232.1
        },
        "PE": {
          "strikePrice": 3600,
          "expiryDate": "31-Jul-2025",
          "underlying": "SUPREMEIND",
          "identifier": "OPTSTKSUPREMEIND31-07-2025PE3600.00",
          "openInterest": 54,
          "changeinOpenInterest": -4,
          "pchangeinOpenInterest": -6.896551724137931,
          "totalTradedVolume": 6,
          "impliedVolatility": 40.35,
          "lastPrice": 3.05,
          "change": -4.25,
          "pChange": -58.21917808219178,
          "totalBuyQuantity": 21000,
          "totalSellQuantity": 9100,
          "bidQty": 175,
          "bidprice": 2.35,
          "askQty": 175,
          "askPrice": 3.95,
          "underlyingValue": 4232.1
        }
      },
      {
        "strikePrice": 3600,
        "expiryDate": "28-Aug-2025",
        "CE": {
          "strikePrice": 3600,
          "expiryDate": "28-Aug-2025",
          "underlying": "SUPREMEIND",
          "identifier": "OPTSTKSUPREMEIND28-08-2025CE3600.00",
          "openInterest": 0,
          "changeinOpenInterest": 0,
          "pchangeinOpenInterest": 0,
          "totalTradedVolume": 0,
          "impliedVolatility": 0,
          "lastPrice": 0,
          "change": 0,
          "pChange": 0,
          "totalBuyQuantity": 2450,
          "totalSellQuantity": 2450,
          "bidQty": 700,
          "bidprice": 661.15,
          "askQty": 700,
          "askPrice": 769.1,
          "underlyingValue": 4232.1
        },
        "PE": {
          "strikePrice": 3600,
          "expiryDate": "28-Aug-2025",
          "underlying": "SUPREMEIND",
          "identifier": "OPTSTKSUPREMEIND28-08-2025PE3600.00",
          "openInterest": 18,
          "changeinOpenInterest": 16,
          "pchangeinOpenInterest": 800,
          "totalTradedVolume": 29,
          "impliedVolatility": 42.11,
          "lastPrice": 32.5,
          "change": -17.5,
          "pChange": -35,
          "totalBuyQuantity": 4550,
          "totalSellQuantity": 2450,
          "bidQty": 175,
          "bidprice": 19.55,
          "askQty": 700,
          "askPrice": 70.65,
          "underlyingValue": 4232.1
        }
      },
      {
        "strikePrice": 3700,
        "expiryDate": "31-Jul-2025",
        "CE": {
          "strikePrice": 3700,
          "expiryDate": "31-Jul-2025",
          "underlying": "SUPREMEIND",
          "identifier": "OPTSTKSUPREMEIND31-07-2025CE3700.00",
          "openInterest": 0,
          "changeinOpenInterest": 0,
          "pchangeinOpenInterest": 0,
          "totalTradedVolume": 0,
          "impliedVolatility": 0,
          "lastPrice": 0,
          "change": 0,
          "pChange": 0,
          "totalBuyQuantity": 10325,
          "totalSellQuantity": 9450,
          "bidQty": 700,
          "bidprice": 544.5,
          "askQty": 1750,
          "askPrice": 590.15,
          "underlyingValue": 4232.1
        },
        "PE": {
          "strikePrice": 3700,
          "expiryDate": "31-Jul-2025",
          "underlying": "SUPREMEIND",
          "identifier": "OPTSTKSUPREMEIND31-07-2025PE3700.00",
          "openInterest": 62,
          "changeinOpenInterest": 28,
          "pchangeinOpenInterest": 82.3529411764706,
          "totalTradedVolume": 62,
          "impliedVolatility": 36.28,
          "lastPrice": 4,
          "change": -7.300000000000001,
          "pChange": -64.60176991150442,
          "totalBuyQuantity": 23450,
          "totalSellQuantity": 16450,
          "bidQty": 175,
          "bidprice": 3.85,
          "askQty": 175,
          "askPrice": 9.65,
          "underlyingValue": 4232.1
        }
      },
      {
        "strikePrice": 3700,
        "expiryDate": "28-Aug-2025",
        "PE": {
          "strikePrice": 3700,
          "expiryDate": "28-Aug-2025",
          "underlying": "SUPREMEIND",
          "identifier": "OPTSTKSUPREMEIND28-08-2025PE3700.00",
          "openInterest": 3,
          "changeinOpenInterest": 3,
          "pchangeinOpenInterest": 0,
          "totalTradedVolume": 5,
          "impliedVolatility": 41.9,
          "lastPrice": 47,
          "change": -91.65,
          "pChange": -66.10169491525424,
          "totalBuyQuantity": 175,
          "totalSellQuantity": 2800,
          "bidQty": 175,
          "bidprice": 30.65,
          "askQty": 350,
          "askPrice": 50,
          "underlyingValue": 4232.1
        },
        "CE": {
          "strikePrice": 3700,
          "expiryDate": "28-Aug-2025",
          "underlying": "SUPREMEIND",
          "identifier": "OPTSTKSUPREMEIND28-08-2025CE3700.00",
          "openInterest": 0,
          "changeinOpenInterest": 0,
          "pchangeinOpenInterest": 0,
          "totalTradedVolume": 0,
          "impliedVolatility": 0,
          "lastPrice": 0,
          "change": 0,
          "pChange": 0,
          "totalBuyQuantity": 3325,
          "totalSellQuantity": 3325,
          "bidQty": 875,
          "bidprice": 555.8,
          "askQty": 875,
          "askPrice": 643.6,
          "underlyingValue": 4232.1
        }
      },
      {
        "strikePrice": 3800,
        "expiryDate": "31-Jul-2025",
        "CE": {
          "strikePrice": 3800,
          "expiryDate": "31-Jul-2025",
          "underlying": "SUPREMEIND",
          "identifier": "OPTSTKSUPREMEIND31-07-2025CE3800.00",
          "openInterest": 4,
          "changeinOpenInterest": 0,
          "pchangeinOpenInterest": 0,
          "totalTradedVolume": 0,
          "impliedVolatility": 0,
          "lastPrice": 625,
          "change": 0,
          "pChange": 0,
          "totalBuyQuantity": 10500,
          "totalSellQuantity": 9450,
          "bidQty": 875,
          "bidprice": 450.7,
          "askQty": 1750,
          "askPrice": 494.8,
          "underlyingValue": 4232.1
        },
        "PE": {
          "strikePrice": 3800,
          "expiryDate": "31-Jul-2025",
          "underlying": "SUPREMEIND",
          "identifier": "OPTSTKSUPREMEIND31-07-2025PE3800.00",
          "openInterest": 58,
          "changeinOpenInterest": -3,
          "pchangeinOpenInterest": -4.918032786885246,
          "totalTradedVolume": 83,
          "impliedVolatility": 36.45,
          "lastPrice": 9.6,
          "change": -13.000000000000002,
          "pChange": -57.52212389380531,
          "totalBuyQuantity": 23800,
          "totalSellQuantity": 20125,
          "bidQty": 175,
          "bidprice": 9.2,
          "askQty": 175,
          "askPrice": 12.55,
          "underlyingValue": 4232.1
        }
      },
      {
        "strikePrice": 3800,
        "expiryDate": "28-Aug-2025",
        "PE": {
          "strikePrice": 3800,
          "expiryDate": "28-Aug-2025",
          "underlying": "SUPREMEIND",
          "identifier": "OPTSTKSUPREMEIND28-08-2025PE3800.00",
          "openInterest": 0,
          "changeinOpenInterest": 0,
          "pchangeinOpenInterest": 0,
          "totalTradedVolume": 0,
          "impliedVolatility": 0,
          "lastPrice": 0,
          "change": 0,
          "pChange": 0,
          "totalBuyQuantity": 0,
          "totalSellQuantity": 0,
          "bidQty": 0,
          "bidprice": 0,
          "askQty": 0,
          "askPrice": 0,
          "underlyingValue": 4232.1
        },
        "CE": {
          "strikePrice": 3800,
          "expiryDate": "28-Aug-2025",
          "underlying": "SUPREMEIND",
          "identifier": "OPTSTKSUPREMEIND28-08-2025CE3800.00",
          "openInterest": 0,
          "changeinOpenInterest": 0,
          "pchangeinOpenInterest": 0,
          "totalTradedVolume": 0,
          "impliedVolatility": 0,
          "lastPrice": 0,
          "change": 0,
          "pChange": 0,
          "totalBuyQuantity": 2450,
          "totalSellQuantity": 0,
          "bidQty": 700,
          "bidprice": 456.7,
          "askQty": 0,
          "askPrice": 0,
          "underlyingValue": 4232.1
        }
      },
      {
        "strikePrice": 3900,
        "expiryDate": "31-Jul-2025",
        "PE": {
          "strikePrice": 3900,
          "expiryDate": "31-Jul-2025",
          "underlying": "SUPREMEIND",
          "identifier": "OPTSTKSUPREMEIND31-07-2025PE3900.00",
          "openInterest": 22,
          "changeinOpenInterest": 5,
          "pchangeinOpenInterest": 29.41176470588235,
          "totalTradedVolume": 28,
          "impliedVolatility": 35.28,
          "lastPrice": 18,
          "change": -23.65,
          "pChange": -56.78271308523409,
          "totalBuyQuantity": 21700,
          "totalSellQuantity": 6475,
          "bidQty": 175,
          "bidprice": 18.6,
          "askQty": 175,
          "askPrice": 31.8,
          "underlyingValue": 4232.1
        },
        "CE": {
          "strikePrice": 3900,
          "expiryDate": "31-Jul-2025",
          "underlying": "SUPREMEIND",
          "identifier": "OPTSTKSUPREMEIND31-07-2025CE3900.00",
          "openInterest": 3,
          "changeinOpenInterest": 0,
          "pchangeinOpenInterest": 0,
          "totalTradedVolume": 0,
          "impliedVolatility": 0,
          "lastPrice": 535,
          "change": 0,
          "pChange": 0,
          "totalBuyQuantity": 8400,
          "totalSellQuantity": 9450,
          "bidQty": 700,
          "bidprice": 356,
          "askQty": 700,
          "askPrice": 405.5,
          "underlyingValue": 4232.1
        }
      },
      {
        "strikePrice": 3900,
        "expiryDate": "28-Aug-2025",
        "CE": {
          "strikePrice": 3900,
          "expiryDate": "28-Aug-2025",
          "underlying": "SUPREMEIND",
          "identifier": "OPTSTKSUPREMEIND28-08-2025CE3900.00",
          "openInterest": 0,
          "changeinOpenInterest": 0,
          "pchangeinOpenInterest": 0,
          "totalTradedVolume": 0,
          "impliedVolatility": 0,
          "lastPrice": 0,
          "change": 0,
          "pChange": 0,
          "totalBuyQuantity": 2450,
          "totalSellQuantity": 0,
          "bidQty": 700,
          "bidprice": 361.7,
          "askQty": 0,
          "askPrice": 0,
          "underlyingValue": 4232.1
        },
        "PE": {
          "strikePrice": 3900,
          "expiryDate": "28-Aug-2025",
          "underlying": "SUPREMEIND",
          "identifier": "OPTSTKSUPREMEIND28-08-2025PE3900.00",
          "openInterest": 2,
          "changeinOpenInterest": 1,
          "pchangeinOpenInterest": 100,
          "totalTradedVolume": 3,
          "impliedVolatility": 38.57,
          "lastPrice": 77.15,
          "change": -21.849999999999994,
          "pChange": -22.070707070707066,
          "totalBuyQuantity": 0,
          "totalSellQuantity": 0,
          "bidQty": 0,
          "bidprice": 0,
          "askQty": 0,
          "askPrice": 0,
          "underlyingValue": 4232.1
        }
      },
      {
        "strikePrice": 3950,
        "expiryDate": "31-Jul-2025",
        "PE": {
          "strikePrice": 3950,
          "expiryDate": "31-Jul-2025",
          "underlying": "SUPREMEIND",
          "identifier": "OPTSTKSUPREMEIND31-07-2025PE3950.00",
          "openInterest": 14,
          "changeinOpenInterest": 4,
          "pchangeinOpenInterest": 40,
          "totalTradedVolume": 13,
          "impliedVolatility": 34.98,
          "lastPrice": 24.8,
          "change": -28.95,
          "pChange": -53.860465116279066,
          "totalBuyQuantity": 6300,
          "totalSellQuantity": 5775,
          "bidQty": 175,
          "bidprice": 7.2,
          "askQty": 175,
          "askPrice": 48.1,
          "underlyingValue": 4232.1
        }
      },
      {
        "strikePrice": 4000,
        "expiryDate": "31-Jul-2025",
        "CE": {
          "strikePrice": 4000,
          "expiryDate": "31-Jul-2025",
          "underlying": "SUPREMEIND",
          "identifier": "OPTSTKSUPREMEIND31-07-2025CE4000.00",
          "openInterest": 14,
          "changeinOpenInterest": 4,
          "pchangeinOpenInterest": 40,
          "totalTradedVolume": 11,
          "impliedVolatility": 39.78,
          "lastPrice": 296,
          "change": 98.9,
          "pChange": 50.177574835109084,
          "totalBuyQuantity": 11725,
          "totalSellQuantity": 11025,
          "bidQty": 525,
          "bidprice": 272.95,
          "askQty": 175,
          "askPrice": 298.55,
          "underlyingValue": 4232.1
        },
        "PE": {
          "strikePrice": 4000,
          "expiryDate": "31-Jul-2025",
          "underlying": "SUPREMEIND",
          "identifier": "OPTSTKSUPREMEIND31-07-2025PE4000.00",
          "openInterest": 153,
          "changeinOpenInterest": -14,
          "pchangeinOpenInterest": -8.383233532934131,
          "totalTradedVolume": 108,
          "impliedVolatility": 36.1,
          "lastPrice": 37,
          "change": -33.849999999999994,
          "pChange": -47.77699364855328,
          "totalBuyQuantity": 20475,
          "totalSellQuantity": 10850,
          "bidQty": 175,
          "bidprice": 32.4,
          "askQty": 175,
          "askPrice": 44.65,
          "underlyingValue": 4232.1
        }
      },
      {
        "strikePrice": 4000,
        "expiryDate": "28-Aug-2025",
        "PE": {
          "strikePrice": 4000,
          "expiryDate": "28-Aug-2025",
          "underlying": "SUPREMEIND",
          "identifier": "OPTSTKSUPREMEIND28-08-2025PE4000.00",
          "openInterest": 0,
          "changeinOpenInterest": 0,
          "pchangeinOpenInterest": 0,
          "totalTradedVolume": 0,
          "impliedVolatility": 0,
          "lastPrice": 0,
          "change": 0,
          "pChange": 0,
          "totalBuyQuantity": 0,
          "totalSellQuantity": 2625,
          "bidQty": 0,
          "bidprice": 0,
          "askQty": 175,
          "askPrice": 180,
          "underlyingValue": 4232.1
        },
        "CE": {
          "strikePrice": 4000,
          "expiryDate": "28-Aug-2025",
          "underlying": "SUPREMEIND",
          "identifier": "OPTSTKSUPREMEIND28-08-2025CE4000.00",
          "openInterest": 0,
          "changeinOpenInterest": 0,
          "pchangeinOpenInterest": 0,
          "totalTradedVolume": 0,
          "impliedVolatility": 0,
          "lastPrice": 0,
          "change": 0,
          "pChange": 0,
          "totalBuyQuantity": 2450,
          "totalSellQuantity": 875,
          "bidQty": 1750,
          "bidprice": 264.85,
          "askQty": 875,
          "askPrice": 506.9,
          "underlyingValue": 4232.1
        }
      },
      {
        "strikePrice": 4100,
        "expiryDate": "31-Jul-2025",
        "CE": {
          "strikePrice": 4100,
          "expiryDate": "31-Jul-2025",
          "underlying": "SUPREMEIND",
          "identifier": "OPTSTKSUPREMEIND31-07-2025CE4100.00",
          "openInterest": 56,
          "changeinOpenInterest": -5,
          "pchangeinOpenInterest": -8.19672131147541,
          "totalTradedVolume": 112,
          "impliedVolatility": 35.99,
          "lastPrice": 214,
          "change": 73.65,
          "pChange": 52.4759529747061,
          "totalBuyQuantity": 8750,
          "totalSellQuantity": 13125,
          "bidQty": 175,
          "bidprice": 196,
          "askQty": 175,
          "askPrice": 216.35,
          "underlyingValue": 4232.1
        },
        "PE": {
          "strikePrice": 4100,
          "expiryDate": "31-Jul-2025",
          "underlying": "SUPREMEIND",
          "identifier": "OPTSTKSUPREMEIND31-07-2025PE4100.00",
          "openInterest": 98,
          "changeinOpenInterest": 37,
          "pchangeinOpenInterest": 60.65573770491803,
          "totalTradedVolume": 112,
          "impliedVolatility": 35.17,
          "lastPrice": 61.45,
          "change": -48.64999999999999,
          "pChange": -44.18710263396911,
          "totalBuyQuantity": 12775,
          "totalSellQuantity": 8225,
          "bidQty": 175,
          "bidprice": 52.45,
          "askQty": 175,
          "askPrice": 67.6,
          "underlyingValue": 4232.1
        }
      },
      {
        "strikePrice": 4100,
        "expiryDate": "28-Aug-2025",
        "PE": {
          "strikePrice": 4100,
          "expiryDate": "28-Aug-2025",
          "underlying": "SUPREMEIND",
          "identifier": "OPTSTKSUPREMEIND28-08-2025PE4100.00",
          "openInterest": 0,
          "changeinOpenInterest": 0,
          "pchangeinOpenInterest": 0,
          "totalTradedVolume": 0,
          "impliedVolatility": 0,
          "lastPrice": 0,
          "change": 0,
          "pChange": 0,
          "totalBuyQuantity": 0,
          "totalSellQuantity": 2450,
          "bidQty": 0,
          "bidprice": 0,
          "askQty": 700,
          "askPrice": 202.4,
          "underlyingValue": 4232.1
        },
        "CE": {
          "strikePrice": 4100,
          "expiryDate": "28-Aug-2025",
          "underlying": "SUPREMEIND",
          "identifier": "OPTSTKSUPREMEIND28-08-2025CE4100.00",
          "openInterest": 0,
          "changeinOpenInterest": 0,
          "pchangeinOpenInterest": 0,
          "totalTradedVolume": 0,
          "impliedVolatility": 0,
          "lastPrice": 0,
          "change": 0,
          "pChange": 0,
          "totalBuyQuantity": 2450,
          "totalSellQuantity": 2800,
          "bidQty": 700,
          "bidprice": 200.45,
          "askQty": 175,
          "askPrice": 396.05,
          "underlyingValue": 4232.1
        }
      },
      {
        "strikePrice": 4150,
        "expiryDate": "31-Jul-2025",
        "PE": {
          "strikePrice": 4150,
          "expiryDate": "31-Jul-2025",
          "underlying": "SUPREMEIND",
          "identifier": "OPTSTKSUPREMEIND31-07-2025PE4150.00",
          "openInterest": 47,
          "changeinOpenInterest": 0,
          "pchangeinOpenInterest": 0,
          "totalTradedVolume": 25,
          "impliedVolatility": 34.87,
          "lastPrice": 78.15,
          "change": -72.04999999999998,
          "pChange": -47.969374167776294,
          "totalBuyQuantity": 5600,
          "totalSellQuantity": 6475,
          "bidQty": 175,
          "bidprice": 67.95,
          "askQty": 350,
          "askPrice": 89.95,
          "underlyingValue": 4232.1
        },
        "CE": {
          "strikePrice": 4150,
          "expiryDate": "31-Jul-2025",
          "underlying": "SUPREMEIND",
          "identifier": "OPTSTKSUPREMEIND31-07-2025CE4150.00",
          "openInterest": 9,
          "changeinOpenInterest": -7,
          "pchangeinOpenInterest": -43.75,
          "totalTradedVolume": 35,
          "impliedVolatility": 35.62,
          "lastPrice": 180.9,
          "change": 71.05000000000001,
          "pChange": 64.67910787437417,
          "totalBuyQuantity": 6300,
          "totalSellQuantity": 3500,
          "bidQty": 175,
          "bidprice": 155.05,
          "askQty": 175,
          "askPrice": 197.8,
          "underlyingValue": 4232.1
        }
      },
      {
        "strikePrice": 4200,
        "expiryDate": "31-Jul-2025",
        "PE": {
          "strikePrice": 4200,
          "expiryDate": "31-Jul-2025",
          "underlying": "SUPREMEIND",
          "identifier": "OPTSTKSUPREMEIND31-07-2025PE4200.00",
          "openInterest": 156,
          "changeinOpenInterest": -12,
          "pchangeinOpenInterest": -7.142857142857143,
          "totalTradedVolume": 225,
          "impliedVolatility": 34.78,
          "lastPrice": 98.6,
          "change": -71.4,
          "pChange": -42.00000000000001,
          "totalBuyQuantity": 15750,
          "totalSellQuantity": 16450,
          "bidQty": 175,
          "bidprice": 90.05,
          "askQty": 350,
          "askPrice": 101.5,
          "underlyingValue": 4232.1
        },
        "CE": {
          "strikePrice": 4200,
          "expiryDate": "31-Jul-2025",
          "underlying": "SUPREMEIND",
          "identifier": "OPTSTKSUPREMEIND31-07-2025CE4200.00",
          "openInterest": 170,
          "changeinOpenInterest": 25,
          "pchangeinOpenInterest": 17.24137931034483,
          "totalTradedVolume": 559,
          "impliedVolatility": 36.78,
          "lastPrice": 156,
          "change": 59.400000000000006,
          "pChange": 61.49068322981367,
          "totalBuyQuantity": 13650,
          "totalSellQuantity": 18025,
          "bidQty": 175,
          "bidprice": 150.05,
          "askQty": 175,
          "askPrice": 154.7,
          "underlyingValue": 4232.1
        }
      },
      {
        "strikePrice": 4200,
        "expiryDate": "28-Aug-2025",
        "PE": {
          "strikePrice": 4200,
          "expiryDate": "28-Aug-2025",
          "underlying": "SUPREMEIND",
          "identifier": "OPTSTKSUPREMEIND28-08-2025PE4200.00",
          "openInterest": 3,
          "changeinOpenInterest": 2,
          "pchangeinOpenInterest": 200,
          "totalTradedVolume": 5,
          "impliedVolatility": 36.95,
          "lastPrice": 175.65,
          "change": 19.599999999999994,
          "pChange": 12.560076898429987,
          "totalBuyQuantity": 875,
          "totalSellQuantity": 2800,
          "bidQty": 175,
          "bidprice": 153.15,
          "askQty": 175,
          "askPrice": 186.6,
          "underlyingValue": 4232.1
        },
        "CE": {
          "strikePrice": 4200,
          "expiryDate": "28-Aug-2025",
          "underlying": "SUPREMEIND",
          "identifier": "OPTSTKSUPREMEIND28-08-2025CE4200.00",
          "openInterest": 0,
          "changeinOpenInterest": 0,
          "pchangeinOpenInterest": 0,
          "totalTradedVolume": 0,
          "impliedVolatility": 0,
          "lastPrice": 0,
          "change": 0,
          "pChange": 0,
          "totalBuyQuantity": 2625,
          "totalSellQuantity": 2625,
          "bidQty": 175,
          "bidprice": 209,
          "askQty": 175,
          "askPrice": 289.05,
          "underlyingValue": 4232.1
        }
      },
      {
        "strikePrice": 4250,
        "expiryDate": "31-Jul-2025",
        "PE": {
          "strikePrice": 4250,
          "expiryDate": "31-Jul-2025",
          "underlying": "SUPREMEIND",
          "identifier": "OPTSTKSUPREMEIND31-07-2025PE4250.00",
          "openInterest": 46,
          "changeinOpenInterest": 7,
          "pchangeinOpenInterest": 17.94871794871795,
          "totalTradedVolume": 28,
          "impliedVolatility": 34.8,
          "lastPrice": 122.65,
          "change": -89.4,
          "pChange": -42.15986795567083,
          "totalBuyQuantity": 11725,
          "totalSellQuantity": 2275,
          "bidQty": 175,
          "bidprice": 122.2,
          "askQty": 350,
          "askPrice": 137.95,
          "underlyingValue": 4232.1
        },
        "CE": {
          "strikePrice": 4250,
          "expiryDate": "31-Jul-2025",
          "underlying": "SUPREMEIND",
          "identifier": "OPTSTKSUPREMEIND31-07-2025CE4250.00",
          "openInterest": 64,
          "changeinOpenInterest": 16,
          "pchangeinOpenInterest": 33.333333333333336,
          "totalTradedVolume": 165,
          "impliedVolatility": 36.17,
          "lastPrice": 128.15,
          "change": 51.400000000000006,
          "pChange": 66.97068403908796,
          "totalBuyQuantity": 16800,
          "totalSellQuantity": 7000,
          "bidQty": 175,
          "bidprice": 128,
          "askQty": 350,
          "askPrice": 143.95,
          "underlyingValue": 4232.1
        }
      },
      {
        "strikePrice": 4300,
        "expiryDate": "31-Jul-2025",
        "PE": {
          "strikePrice": 4300,
          "expiryDate": "31-Jul-2025",
          "underlying": "SUPREMEIND",
          "identifier": "OPTSTKSUPREMEIND31-07-2025PE4300.00",
          "openInterest": 198,
          "changeinOpenInterest": -67,
          "pchangeinOpenInterest": -25.28301886792453,
          "totalTradedVolume": 131,
          "impliedVolatility": 34.36,
          "lastPrice": 148.25,
          "change": -76.80000000000001,
          "pChange": -34.125749833370364,
          "totalBuyQuantity": 10500,
          "totalSellQuantity": 10500,
          "bidQty": 175,
          "bidprice": 147.6,
          "askQty": 175,
          "askPrice": 161.1,
          "underlyingValue": 4232.1
        },
        "CE": {
          "strikePrice": 4300,
          "expiryDate": "31-Jul-2025",
          "underlying": "SUPREMEIND",
          "identifier": "OPTSTKSUPREMEIND31-07-2025CE4300.00",
          "openInterest": 294,
          "changeinOpenInterest": -55,
          "pchangeinOpenInterest": -15.759312320916905,
          "totalTradedVolume": 928,
          "impliedVolatility": 36.17,
          "lastPrice": 105.5,
          "change": 44.7,
          "pChange": 73.51973684210527,
          "totalBuyQuantity": 25200,
          "totalSellQuantity": 16450,
          "bidQty": 350,
          "bidprice": 104,
          "askQty": 175,
          "askPrice": 105.5,
          "underlyingValue": 4232.1
        }
      },
      {
        "strikePrice": 4300,
        "expiryDate": "28-Aug-2025",
        "CE": {
          "strikePrice": 4300,
          "expiryDate": "28-Aug-2025",
          "underlying": "SUPREMEIND",
          "identifier": "OPTSTKSUPREMEIND28-08-2025CE4300.00",
          "openInterest": 0,
          "changeinOpenInterest": 0,
          "pchangeinOpenInterest": 0,
          "totalTradedVolume": 0,
          "impliedVolatility": 0,
          "lastPrice": 0,
          "change": 0,
          "pChange": 0,
          "totalBuyQuantity": 2450,
          "totalSellQuantity": 0,
          "bidQty": 700,
          "bidprice": 100.2,
          "askQty": 0,
          "askPrice": 0,
          "underlyingValue": 4232.1
        },
        "PE": {
          "strikePrice": 4300,
          "expiryDate": "28-Aug-2025",
          "underlying": "SUPREMEIND",
          "identifier": "OPTSTKSUPREMEIND28-08-2025PE4300.00",
          "openInterest": 0,
          "changeinOpenInterest": 0,
          "pchangeinOpenInterest": 0,
          "totalTradedVolume": 0,
          "impliedVolatility": 0,
          "lastPrice": 0,
          "change": 0,
          "pChange": 0,
          "totalBuyQuantity": 0,
          "totalSellQuantity": 700,
          "bidQty": 0,
          "bidprice": 0,
          "askQty": 700,
          "askPrice": 350.25,
          "underlyingValue": 4232.1
        }
      },
      {
        "strikePrice": 4350,
        "expiryDate": "31-Jul-2025",
        "CE": {
          "strikePrice": 4350,
          "expiryDate": "31-Jul-2025",
          "underlying": "SUPREMEIND",
          "identifier": "OPTSTKSUPREMEIND31-07-2025CE4350.00",
          "openInterest": 78,
          "changeinOpenInterest": 9,
          "pchangeinOpenInterest": 13.043478260869565,
          "totalTradedVolume": 41,
          "impliedVolatility": 35.63,
          "lastPrice": 84,
          "change": 37.35,
          "pChange": 80.06430868167203,
          "totalBuyQuantity": 21525,
          "totalSellQuantity": 16800,
          "bidQty": 175,
          "bidprice": 82.35,
          "askQty": 175,
          "askPrice": 85,
          "underlyingValue": 4232.1
        },
        "PE": {
          "strikePrice": 4350,
          "expiryDate": "31-Jul-2025",
          "underlying": "SUPREMEIND",
          "identifier": "OPTSTKSUPREMEIND31-07-2025PE4350.00",
          "openInterest": 61,
          "changeinOpenInterest": 1,
          "pchangeinOpenInterest": 1.6666666666666667,
          "totalTradedVolume": 3,
          "impliedVolatility": 38.52,
          "lastPrice": 192.75,
          "change": -75.80000000000001,
          "pChange": -28.225656302364555,
          "totalBuyQuantity": 5950,
          "totalSellQuantity": 12600,
          "bidQty": 175,
          "bidprice": 167.2,
          "askQty": 175,
          "askPrice": 187.5,
          "underlyingValue": 4232.1
        }
      },
      {
        "strikePrice": 4400,
        "expiryDate": "31-Jul-2025",
        "CE": {
          "strikePrice": 4400,
          "expiryDate": "31-Jul-2025",
          "underlying": "SUPREMEIND",
          "identifier": "OPTSTKSUPREMEIND31-07-2025CE4400.00",
          "openInterest": 416,
          "changeinOpenInterest": 16,
          "pchangeinOpenInterest": 4,
          "totalTradedVolume": 293,
          "impliedVolatility": 35.23,
          "lastPrice": 66,
          "change": 28.85,
          "pChange": 77.65814266487214,
          "totalBuyQuantity": 27125,
          "totalSellQuantity": 15750,
          "bidQty": 175,
          "bidprice": 65.65,
          "askQty": 175,
          "askPrice": 67.8,
          "underlyingValue": 4232.1
        },
        "PE": {
          "strikePrice": 4400,
          "expiryDate": "31-Jul-2025",
          "underlying": "SUPREMEIND",
          "identifier": "OPTSTKSUPREMEIND31-07-2025PE4400.00",
          "openInterest": 117,
          "changeinOpenInterest": 0,
          "pchangeinOpenInterest": 0,
          "totalTradedVolume": 3,
          "impliedVolatility": 34.31,
          "lastPrice": 211.7,
          "change": -95.90000000000003,
          "pChange": -31.17685305591678,
          "totalBuyQuantity": 5250,
          "totalSellQuantity": 12600,
          "bidQty": 175,
          "bidprice": 202.15,
          "askQty": 175,
          "askPrice": 215,
          "underlyingValue": 4232.1
        }
      },
      {
        "strikePrice": 4400,
        "expiryDate": "28-Aug-2025",
        "CE": {
          "strikePrice": 4400,
          "expiryDate": "28-Aug-2025",
          "underlying": "SUPREMEIND",
          "identifier": "OPTSTKSUPREMEIND28-08-2025CE4400.00",
          "openInterest": 0,
          "changeinOpenInterest": 0,
          "pchangeinOpenInterest": 0,
          "totalTradedVolume": 0,
          "impliedVolatility": 0,
          "lastPrice": 0,
          "change": 0,
          "pChange": 0,
          "totalBuyQuantity": 2450,
          "totalSellQuantity": 2975,
          "bidQty": 700,
          "bidprice": 98.4,
          "askQty": 175,
          "askPrice": 207.75,
          "underlyingValue": 4232.1
        },
        "PE": {
          "strikePrice": 4400,
          "expiryDate": "28-Aug-2025",
          "underlying": "SUPREMEIND",
          "identifier": "OPTSTKSUPREMEIND28-08-2025PE4400.00",
          "openInterest": 0,
          "changeinOpenInterest": 0,
          "pchangeinOpenInterest": 0,
          "totalTradedVolume": 0,
          "impliedVolatility": 0,
          "lastPrice": 0,
          "change": 0,
          "pChange": 0,
          "totalBuyQuantity": 0,
          "totalSellQuantity": 2450,
          "bidQty": 0,
          "bidprice": 0,
          "askQty": 700,
          "askPrice": 357.4,
          "underlyingValue": 4232.1
        }
      },
      {
        "strikePrice": 4450,
        "expiryDate": "31-Jul-2025",
        "PE": {
          "strikePrice": 4450,
          "expiryDate": "31-Jul-2025",
          "underlying": "SUPREMEIND",
          "identifier": "OPTSTKSUPREMEIND31-07-2025PE4450.00",
          "openInterest": 32,
          "changeinOpenInterest": 0,
          "pchangeinOpenInterest": 0,
          "totalTradedVolume": 0,
          "impliedVolatility": 0,
          "lastPrice": 274.95,
          "change": 0,
          "pChange": 0,
          "totalBuyQuantity": 5250,
          "totalSellQuantity": 10850,
          "bidQty": 525,
          "bidprice": 219.05,
          "askQty": 700,
          "askPrice": 274.2,
          "underlyingValue": 4232.1
        },
        "CE": {
          "strikePrice": 4450,
          "expiryDate": "31-Jul-2025",
          "underlying": "SUPREMEIND",
          "identifier": "OPTSTKSUPREMEIND31-07-2025CE4450.00",
          "openInterest": 29,
          "changeinOpenInterest": 0,
          "pchangeinOpenInterest": 0,
          "totalTradedVolume": 3,
          "impliedVolatility": 34.11,
          "lastPrice": 48.7,
          "change": 18.050000000000004,
          "pChange": 58.890701468189256,
          "totalBuyQuantity": 15575,
          "totalSellQuantity": 8225,
          "bidQty": 175,
          "bidprice": 48.8,
          "askQty": 700,
          "askPrice": 83.4,
          "underlyingValue": 4232.1
        }
      },
      {
        "strikePrice": 4500,
        "expiryDate": "31-Jul-2025",
        "CE": {
          "strikePrice": 4500,
          "expiryDate": "31-Jul-2025",
          "underlying": "SUPREMEIND",
          "identifier": "OPTSTKSUPREMEIND31-07-2025CE4500.00",
          "openInterest": 408,
          "changeinOpenInterest": -38,
          "pchangeinOpenInterest": -8.52017937219731,
          "totalTradedVolume": 581,
          "impliedVolatility": 35.46,
          "lastPrice": 41.1,
          "change": 18.150000000000002,
          "pChange": 79.08496732026144,
          "totalBuyQuantity": 29225,
          "totalSellQuantity": 19425,
          "bidQty": 175,
          "bidprice": 38.05,
          "askQty": 350,
          "askPrice": 41.75,
          "underlyingValue": 4232.1
        },
        "PE": {
          "strikePrice": 4500,
          "expiryDate": "31-Jul-2025",
          "underlying": "SUPREMEIND",
          "identifier": "OPTSTKSUPREMEIND31-07-2025PE4500.00",
          "openInterest": 162,
          "changeinOpenInterest": -1,
          "pchangeinOpenInterest": -0.6134969325153374,
          "totalTradedVolume": 2,
          "impliedVolatility": 34.63,
          "lastPrice": 287.1,
          "change": -120.75,
          "pChange": -29.60647296800294,
          "totalBuyQuantity": 6300,
          "totalSellQuantity": 13475,
          "bidQty": 350,
          "bidprice": 272.45,
          "askQty": 175,
          "askPrice": 300.5,
          "underlyingValue": 4232.1
        }
      },
      {
        "strikePrice": 4500,
        "expiryDate": "28-Aug-2025",
        "PE": {
          "strikePrice": 4500,
          "expiryDate": "28-Aug-2025",
          "underlying": "SUPREMEIND",
          "identifier": "OPTSTKSUPREMEIND28-08-2025PE4500.00",
          "openInterest": 0,
          "changeinOpenInterest": 0,
          "pchangeinOpenInterest": 0,
          "totalTradedVolume": 0,
          "impliedVolatility": 0,
          "lastPrice": 0,
          "change": 0,
          "pChange": 0,
          "totalBuyQuantity": 3325,
          "totalSellQuantity": 2450,
          "bidQty": 875,
          "bidprice": 315.45,
          "askQty": 700,
          "askPrice": 376.5,
          "underlyingValue": 4232.1
        },
        "CE": {
          "strikePrice": 4500,
          "expiryDate": "28-Aug-2025",
          "underlying": "SUPREMEIND",
          "identifier": "OPTSTKSUPREMEIND28-08-2025CE4500.00",
          "openInterest": 7,
          "changeinOpenInterest": 7,
          "pchangeinOpenInterest": 0,
          "totalTradedVolume": 7,
          "impliedVolatility": 37.11,
          "lastPrice": 132,
          "change": -186.5,
          "pChange": -58.55572998430141,
          "totalBuyQuantity": 2975,
          "totalSellQuantity": 3150,
          "bidQty": 175,
          "bidprice": 115.4,
          "askQty": 350,
          "askPrice": 132.95,
          "underlyingValue": 4232.1
        }
      },
      {
        "strikePrice": 4550,
        "expiryDate": "31-Jul-2025",
        "PE": {
          "strikePrice": 4550,
          "expiryDate": "31-Jul-2025",
          "underlying": "SUPREMEIND",
          "identifier": "OPTSTKSUPREMEIND31-07-2025PE4550.00",
          "openInterest": 14,
          "changeinOpenInterest": 0,
          "pchangeinOpenInterest": 0,
          "totalTradedVolume": 0,
          "impliedVolatility": 0,
          "lastPrice": 415.65,
          "change": 0,
          "pChange": 0,
          "totalBuyQuantity": 9975,
          "totalSellQuantity": 11375,
          "bidQty": 525,
          "bidprice": 298.05,
          "askQty": 525,
          "askPrice": 355.45,
          "underlyingValue": 4232.1
        },
        "CE": {
          "strikePrice": 4550,
          "expiryDate": "31-Jul-2025",
          "underlying": "SUPREMEIND",
          "identifier": "OPTSTKSUPREMEIND31-07-2025CE4550.00",
          "openInterest": 25,
          "changeinOpenInterest": -6,
          "pchangeinOpenInterest": -19.35483870967742,
          "totalTradedVolume": 16,
          "impliedVolatility": 35.56,
          "lastPrice": 31.9,
          "change": 16.9,
          "pChange": 112.66666666666664,
          "totalBuyQuantity": 21000,
          "totalSellQuantity": 7525,
          "bidQty": 175,
          "bidprice": 17.8,
          "askQty": 175,
          "askPrice": 45.35,
          "underlyingValue": 4232.1
        }
      },
      {
        "strikePrice": 4600,
        "expiryDate": "31-Jul-2025",
        "CE": {
          "strikePrice": 4600,
          "expiryDate": "31-Jul-2025",
          "underlying": "SUPREMEIND",
          "identifier": "OPTSTKSUPREMEIND31-07-2025CE4600.00",
          "openInterest": 214,
          "changeinOpenInterest": 7,
          "pchangeinOpenInterest": 3.3816425120772946,
          "totalTradedVolume": 145,
          "impliedVolatility": 36.04,
          "lastPrice": 25.3,
          "change": 11.100000000000001,
          "pChange": 78.16901408450705,
          "totalBuyQuantity": 23975,
          "totalSellQuantity": 12600,
          "bidQty": 1050,
          "bidprice": 24.45,
          "askQty": 175,
          "askPrice": 26.35,
          "underlyingValue": 4232.1
        },
        "PE": {
          "strikePrice": 4600,
          "expiryDate": "31-Jul-2025",
          "underlying": "SUPREMEIND",
          "identifier": "OPTSTKSUPREMEIND31-07-2025PE4600.00",
          "openInterest": 36,
          "changeinOpenInterest": 0,
          "pchangeinOpenInterest": 0,
          "totalTradedVolume": 0,
          "impliedVolatility": 0,
          "lastPrice": 367.85,
          "change": 0,
          "pChange": 0,
          "totalBuyQuantity": 7700,
          "totalSellQuantity": 10325,
          "bidQty": 700,
          "bidprice": 339.35,
          "askQty": 700,
          "askPrice": 382.2,
          "underlyingValue": 4232.1
        }
      },
      {
        "strikePrice": 4600,
        "expiryDate": "28-Aug-2025",
        "PE": {
          "strikePrice": 4600,
          "expiryDate": "28-Aug-2025",
          "underlying": "SUPREMEIND",
          "identifier": "OPTSTKSUPREMEIND28-08-2025PE4600.00",
          "openInterest": 0,
          "changeinOpenInterest": 0,
          "pchangeinOpenInterest": 0,
          "totalTradedVolume": 0,
          "impliedVolatility": 0,
          "lastPrice": 0,
          "change": 0,
          "pChange": 0,
          "totalBuyQuantity": 0,
          "totalSellQuantity": 1750,
          "bidQty": 0,
          "bidprice": 0,
          "askQty": 1750,
          "askPrice": 513.2,
          "underlyingValue": 4232.1
        },
        "CE": {
          "strikePrice": 4600,
          "expiryDate": "28-Aug-2025",
          "underlying": "SUPREMEIND",
          "identifier": "OPTSTKSUPREMEIND28-08-2025CE4600.00",
          "openInterest": 0,
          "changeinOpenInterest": 0,
          "pchangeinOpenInterest": 0,
          "totalTradedVolume": 0,
          "impliedVolatility": 0,
          "lastPrice": 0,
          "change": 0,
          "pChange": 0,
          "totalBuyQuantity": 0,
          "totalSellQuantity": 2800,
          "bidQty": 0,
          "bidprice": 0,
          "askQty": 175,
          "askPrice": 156.3,
          "underlyingValue": 4232.1
        }
      },
      {
        "strikePrice": 4650,
        "expiryDate": "31-Jul-2025",
        "CE": {
          "strikePrice": 4650,
          "expiryDate": "31-Jul-2025",
          "underlying": "SUPREMEIND",
          "identifier": "OPTSTKSUPREMEIND31-07-2025CE4650.00",
          "openInterest": 46,
          "changeinOpenInterest": 7,
          "pchangeinOpenInterest": 17.94871794871795,
          "totalTradedVolume": 38,
          "impliedVolatility": 36.63,
          "lastPrice": 20.2,
          "change": 9.85,
          "pChange": 95.16908212560386,
          "totalBuyQuantity": 26950,
          "totalSellQuantity": 14525,
          "bidQty": 175,
          "bidprice": 7.1,
          "askQty": 175,
          "askPrice": 30.8,
          "underlyingValue": 4232.1
        },
        "PE": {
          "strikePrice": 4650,
          "expiryDate": "31-Jul-2025",
          "underlying": "SUPREMEIND",
          "identifier": "OPTSTKSUPREMEIND31-07-2025PE4650.00",
          "openInterest": 7,
          "changeinOpenInterest": 0,
          "pchangeinOpenInterest": 0,
          "totalTradedVolume": 0,
          "impliedVolatility": 0,
          "lastPrice": 330.65,
          "change": 0,
          "pChange": 0,
          "totalBuyQuantity": 9625,
          "totalSellQuantity": 5075,
          "bidQty": 175,
          "bidprice": 384.7,
          "askQty": 700,
          "askPrice": 435.6,
          "underlyingValue": 4232.1
        }
      },
      {
        "strikePrice": 4700,
        "expiryDate": "31-Jul-2025",
        "CE": {
          "strikePrice": 4700,
          "expiryDate": "31-Jul-2025",
          "underlying": "SUPREMEIND",
          "identifier": "OPTSTKSUPREMEIND31-07-2025CE4700.00",
          "openInterest": 137,
          "changeinOpenInterest": 8,
          "pchangeinOpenInterest": 6.2015503875969,
          "totalTradedVolume": 873,
          "impliedVolatility": 37.13,
          "lastPrice": 16,
          "change": 5.75,
          "pChange": 56.09756097560976,
          "totalBuyQuantity": 20475,
          "totalSellQuantity": 4375,
          "bidQty": 175,
          "bidprice": 15.55,
          "askQty": 525,
          "askPrice": 16.45,
          "underlyingValue": 4232.1
        },
        "PE": {
          "strikePrice": 4700,
          "expiryDate": "31-Jul-2025",
          "underlying": "SUPREMEIND",
          "identifier": "OPTSTKSUPREMEIND31-07-2025PE4700.00",
          "openInterest": 32,
          "changeinOpenInterest": 0,
          "pchangeinOpenInterest": 0,
          "totalTradedVolume": 0,
          "impliedVolatility": 0,
          "lastPrice": 450.05,
          "change": 0,
          "pChange": 0,
          "totalBuyQuantity": 9450,
          "totalSellQuantity": 10325,
          "bidQty": 1750,
          "bidprice": 426.2,
          "askQty": 700,
          "askPrice": 474.4,
          "underlyingValue": 4232.1
        }
      },
      {
        "strikePrice": 4700,
        "expiryDate": "28-Aug-2025",
        "PE": {
          "strikePrice": 4700,
          "expiryDate": "28-Aug-2025",
          "underlying": "SUPREMEIND",
          "identifier": "OPTSTKSUPREMEIND28-08-2025PE4700.00",
          "openInterest": 0,
          "changeinOpenInterest": 0,
          "pchangeinOpenInterest": 0,
          "totalTradedVolume": 0,
          "impliedVolatility": 0,
          "lastPrice": 0,
          "change": 0,
          "pChange": 0,
          "totalBuyQuantity": 875,
          "totalSellQuantity": 1750,
          "bidQty": 875,
          "bidprice": 413.6,
          "askQty": 1750,
          "askPrice": 589.1,
          "underlyingValue": 4232.1
        }
      },
      {
        "strikePrice": 4750,
        "expiryDate": "31-Jul-2025",
        "CE": {
          "strikePrice": 4750,
          "expiryDate": "31-Jul-2025",
          "underlying": "SUPREMEIND",
          "identifier": "OPTSTKSUPREMEIND31-07-2025CE4750.00",
          "openInterest": 13,
          "changeinOpenInterest": 0,
          "pchangeinOpenInterest": 0,
          "totalTradedVolume": 0,
          "impliedVolatility": 0,
          "lastPrice": 62,
          "change": 0,
          "pChange": 0,
          "totalBuyQuantity": 10850,
          "totalSellQuantity": 0,
          "bidQty": 3500,
          "bidprice": 2.65,
          "askQty": 0,
          "askPrice": 0,
          "underlyingValue": 4232.1
        }
      },
      {
        "strikePrice": 4800,
        "expiryDate": "31-Jul-2025",
        "PE": {
          "strikePrice": 4800,
          "expiryDate": "31-Jul-2025",
          "underlying": "SUPREMEIND",
          "identifier": "OPTSTKSUPREMEIND31-07-2025PE4800.00",
          "openInterest": 2,
          "changeinOpenInterest": 0,
          "pchangeinOpenInterest": 0,
          "totalTradedVolume": 0,
          "impliedVolatility": 0,
          "lastPrice": 402.75,
          "change": 0,
          "pChange": 0,
          "totalBuyQuantity": 9450,
          "totalSellQuantity": 10325,
          "bidQty": 1750,
          "bidprice": 520.15,
          "askQty": 700,
          "askPrice": 568.95,
          "underlyingValue": 4232.1
        },
        "CE": {
          "strikePrice": 4800,
          "expiryDate": "31-Jul-2025",
          "underlying": "SUPREMEIND",
          "identifier": "OPTSTKSUPREMEIND31-07-2025CE4800.00",
          "openInterest": 110,
          "changeinOpenInterest": 26,
          "pchangeinOpenInterest": 30.952380952380953,
          "totalTradedVolume": 51,
          "impliedVolatility": 37.53,
          "lastPrice": 9.3,
          "change": 2.200000000000001,
          "pChange": 30.985915492957762,
          "totalBuyQuantity": 25725,
          "totalSellQuantity": 8050,
          "bidQty": 175,
          "bidprice": 6.55,
          "askQty": 175,
          "askPrice": 14.95,
          "underlyingValue": 4232.1
        }
      },
      {
        "strikePrice": 4800,
        "expiryDate": "28-Aug-2025",
        "PE": {
          "strikePrice": 4800,
          "expiryDate": "28-Aug-2025",
          "underlying": "SUPREMEIND",
          "identifier": "OPTSTKSUPREMEIND28-08-2025PE4800.00",
          "openInterest": 0,
          "changeinOpenInterest": 0,
          "pchangeinOpenInterest": 0,
          "totalTradedVolume": 0,
          "impliedVolatility": 0,
          "lastPrice": 0,
          "change": 0,
          "pChange": 0,
          "totalBuyQuantity": 3325,
          "totalSellQuantity": 1750,
          "bidQty": 875,
          "bidprice": 495.1,
          "askQty": 1750,
          "askPrice": 687.15,
          "underlyingValue": 4232.1
        },
        "CE": {
          "strikePrice": 4800,
          "expiryDate": "28-Aug-2025",
          "underlying": "SUPREMEIND",
          "identifier": "OPTSTKSUPREMEIND28-08-2025CE4800.00",
          "openInterest": 0,
          "changeinOpenInterest": 0,
          "pchangeinOpenInterest": 0,
          "totalTradedVolume": 0,
          "impliedVolatility": 0,
          "lastPrice": 0,
          "change": 0,
          "pChange": 0,
          "totalBuyQuantity": 0,
          "totalSellQuantity": 0,
          "bidQty": 0,
          "bidprice": 0,
          "askQty": 0,
          "askPrice": 0,
          "underlyingValue": 4232.1
        }
      },
      {
        "strikePrice": 4900,
        "expiryDate": "31-Jul-2025",
        "CE": {
          "strikePrice": 4900,
          "expiryDate": "31-Jul-2025",
          "underlying": "SUPREMEIND",
          "identifier": "OPTSTKSUPREMEIND31-07-2025CE4900.00",
          "openInterest": 16,
          "changeinOpenInterest": -2,
          "pchangeinOpenInterest": -11.11111111111111,
          "totalTradedVolume": 3,
          "impliedVolatility": 40.44,
          "lastPrice": 7.4,
          "change": 1.3500000000000005,
          "pChange": 22.314049586776868,
          "totalBuyQuantity": 10325,
          "totalSellQuantity": 3150,
          "bidQty": 175,
          "bidprice": 1.7,
          "askQty": 175,
          "askPrice": 8.5,
          "underlyingValue": 4232.1
        }
      },
      {
        "strikePrice": 5000,
        "expiryDate": "31-Jul-2025",
        "PE": {
          "strikePrice": 5000,
          "expiryDate": "31-Jul-2025",
          "underlying": "SUPREMEIND",
          "identifier": "OPTSTKSUPREMEIND31-07-2025PE5000.00",
          "openInterest": 0,
          "changeinOpenInterest": 0,
          "pchangeinOpenInterest": 0,
          "totalTradedVolume": 0,
          "impliedVolatility": 0,
          "lastPrice": 0,
          "change": 0,
          "pChange": 0,
          "totalBuyQuantity": 9975,
          "totalSellQuantity": 10325,
          "bidQty": 525,
          "bidprice": 717.2,
          "askQty": 700,
          "askPrice": 766.75,
          "underlyingValue": 4232.1
        },
        "CE": {
          "strikePrice": 5000,
          "expiryDate": "31-Jul-2025",
          "underlying": "SUPREMEIND",
          "identifier": "OPTSTKSUPREMEIND31-07-2025CE5000.00",
          "openInterest": 300,
          "changeinOpenInterest": 14,
          "pchangeinOpenInterest": 4.895104895104895,
          "totalTradedVolume": 40,
          "impliedVolatility": 42.81,
          "lastPrice": 5.7,
          "change": 1.7000000000000002,
          "pChange": 42.50000000000001,
          "totalBuyQuantity": 28875,
          "totalSellQuantity": 7525,
          "bidQty": 175,
          "bidprice": 5.1,
          "askQty": 175,
          "askPrice": 5.85,
          "underlyingValue": 4232.1
        }
      },
      {
        "strikePrice": 5000,
        "expiryDate": "28-Aug-2025",
        "CE": {
          "strikePrice": 5000,
          "expiryDate": "28-Aug-2025",
          "underlying": "SUPREMEIND",
          "identifier": "OPTSTKSUPREMEIND28-08-2025CE5000.00",
          "openInterest": 0,
          "changeinOpenInterest": 0,
          "pchangeinOpenInterest": 0,
          "totalTradedVolume": 0,
          "impliedVolatility": 0,
          "lastPrice": 0,
          "change": 0,
          "pChange": 0,
          "totalBuyQuantity": 0,
          "totalSellQuantity": 525,
          "bidQty": 0,
          "bidprice": 0,
          "askQty": 175,
          "askPrice": 60,
          "underlyingValue": 4232.1
        },
        "PE": {
          "strikePrice": 5000,
          "expiryDate": "28-Aug-2025",
          "underlying": "SUPREMEIND",
          "identifier": "OPTSTKSUPREMEIND28-08-2025PE5000.00",
          "openInterest": 0,
          "changeinOpenInterest": 0,
          "pchangeinOpenInterest": 0,
          "totalTradedVolume": 0,
          "impliedVolatility": 0,
          "lastPrice": 0,
          "change": 0,
          "pChange": 0,
          "totalBuyQuantity": 3325,
          "totalSellQuantity": 1750,
          "bidQty": 875,
          "bidprice": 701.55,
          "askQty": 1750,
          "askPrice": 812.3,
          "underlyingValue": 4232.1
        }
      },
      {
        "strikePrice": 5150,
        "expiryDate": "31-Jul-2025",
        "CE": {
          "strikePrice": 5150,
          "expiryDate": "31-Jul-2025",
          "underlying": "SUPREMEIND",
          "identifier": "OPTSTKSUPREMEIND31-07-2025CE5150.00",
          "openInterest": 72,
          "changeinOpenInterest": 8,
          "pchangeinOpenInterest": 12.5,
          "totalTradedVolume": 14,
          "impliedVolatility": 46.31,
          "lastPrice": 4.05,
          "change": 1.5499999999999998,
          "pChange": 61.999999999999986,
          "totalBuyQuantity": 3675,
          "totalSellQuantity": 875,
          "bidQty": 175,
          "bidprice": 0.4,
          "askQty": 175,
          "askPrice": 4.05,
          "underlyingValue": 4232.1
        }
      },
      {
        "strikePrice": 5200,
        "expiryDate": "31-Jul-2025",
        "CE": {
          "strikePrice": 5200,
          "expiryDate": "31-Jul-2025",
          "underlying": "SUPREMEIND",
          "identifier": "OPTSTKSUPREMEIND31-07-2025CE5200.00",
          "openInterest": 75,
          "changeinOpenInterest": 0,
          "pchangeinOpenInterest": 0,
          "totalTradedVolume": 0,
          "impliedVolatility": 0,
          "lastPrice": 1.4,
          "change": 0,
          "pChange": 0,
          "totalBuyQuantity": 7525,
          "totalSellQuantity": 700,
          "bidQty": 350,
          "bidprice": 1.45,
          "askQty": 700,
          "askPrice": 20.15,
          "underlyingValue": 4232.1
        }
      }
    ],
    "timestamp": "15-Jul-2025 15:30:00",
    "underlyingValue": 4232.1,
    "strikePrices": [
      3600,
      3700,
      3800,
      3900,
      3950,
      4000,
      4100,
      4150,
      4200,
      4250,
      4300,
      4350,
      4400,
      4450,
      4500,
      4550,
      4600,
      4650,
      4700,
      4750,
      4800,
      4900,
      5000,
      5150,
      5200
    ]
  },
  "filtered": {
    "data": [
      {
        "strikePrice": 3600,
        "expiryDate": "31-Jul-2025",
        "CE": {
          "strikePrice": 3600,
          "expiryDate": "31-Jul-2025",
          "underlying": "SUPREMEIND",
          "identifier": "OPTSTKSUPREMEIND31-07-2025CE3600.00",
          "openInterest": 0,
          "changeinOpenInterest": 0,
          "pchangeinOpenInterest": 0,
          "totalTradedVolume": 0,
          "impliedVolatility": 0,
          "lastPrice": 0,
          "change": 0,
          "pChange": 0,
          "totalBuyQuantity": 10325,
          "totalSellQuantity": 9450,
          "bidQty": 875,
          "bidprice": 640.8,
          "askQty": 1750,
          "askPrice": 687.6,
          "underlyingValue": 4232.1
        },
        "PE": {
          "strikePrice": 3600,
          "expiryDate": "31-Jul-2025",
          "underlying": "SUPREMEIND",
          "identifier": "OPTSTKSUPREMEIND31-07-2025PE3600.00",
          "openInterest": 54,
          "changeinOpenInterest": -4,
          "pchangeinOpenInterest": -6.896551724137931,
          "totalTradedVolume": 6,
          "impliedVolatility": 40.35,
          "lastPrice": 3.05,
          "change": -4.25,
          "pChange": -58.21917808219178,
          "totalBuyQuantity": 21000,
          "totalSellQuantity": 9100,
          "bidQty": 175,
          "bidprice": 2.35,
          "askQty": 175,
          "askPrice": 3.95,
          "underlyingValue": 4232.1
        }
      },
      {
        "strikePrice": 3700,
        "expiryDate": "31-Jul-2025",
        "CE": {
          "strikePrice": 3700,
          "expiryDate": "31-Jul-2025",
          "underlying": "SUPREMEIND",
          "identifier": "OPTSTKSUPREMEIND31-07-2025CE3700.00",
          "openInterest": 0,
          "changeinOpenInterest": 0,
          "pchangeinOpenInterest": 0,
          "totalTradedVolume": 0,
          "impliedVolatility": 0,
          "lastPrice": 0,
          "change": 0,
          "pChange": 0,
          "totalBuyQuantity": 10325,
          "totalSellQuantity": 9450,
          "bidQty": 700,
          "bidprice": 544.5,
          "askQty": 1750,
          "askPrice": 590.15,
          "underlyingValue": 4232.1
        },
        "PE": {
          "strikePrice": 3700,
          "expiryDate": "31-Jul-2025",
          "underlying": "SUPREMEIND",
          "identifier": "OPTSTKSUPREMEIND31-07-2025PE3700.00",
          "openInterest": 62,
          "changeinOpenInterest": 28,
          "pchangeinOpenInterest": 82.3529411764706,
          "totalTradedVolume": 62,
          "impliedVolatility": 36.28,
          "lastPrice": 4,
          "change": -7.300000000000001,
          "pChange": -64.60176991150442,
          "totalBuyQuantity": 23450,
          "totalSellQuantity": 16450,
          "bidQty": 175,
          "bidprice": 3.85,
          "askQty": 175,
          "askPrice": 9.65,
          "underlyingValue": 4232.1
        }
      },
      {
        "strikePrice": 3800,
        "expiryDate": "31-Jul-2025",
        "CE": {
          "strikePrice": 3800,
          "expiryDate": "31-Jul-2025",
          "underlying": "SUPREMEIND",
          "identifier": "OPTSTKSUPREMEIND31-07-2025CE3800.00",
          "openInterest": 4,
          "changeinOpenInterest": 0,
          "pchangeinOpenInterest": 0,
          "totalTradedVolume": 0,
          "impliedVolatility": 0,
          "lastPrice": 625,
          "change": 0,
          "pChange": 0,
          "totalBuyQuantity": 10500,
          "totalSellQuantity": 9450,
          "bidQty": 875,
          "bidprice": 450.7,
          "askQty": 1750,
          "askPrice": 494.8,
          "underlyingValue": 4232.1
        },
        "PE": {
          "strikePrice": 3800,
          "expiryDate": "31-Jul-2025",
          "underlying": "SUPREMEIND",
          "identifier": "OPTSTKSUPREMEIND31-07-2025PE3800.00",
          "openInterest": 58,
          "changeinOpenInterest": -3,
          "pchangeinOpenInterest": -4.918032786885246,
          "totalTradedVolume": 83,
          "impliedVolatility": 36.45,
          "lastPrice": 9.6,
          "change": -13.000000000000002,
          "pChange": -57.52212389380531,
          "totalBuyQuantity": 23800,
          "totalSellQuantity": 20125,
          "bidQty": 175,
          "bidprice": 9.2,
          "askQty": 175,
          "askPrice": 12.55,
          "underlyingValue": 4232.1
        }
      },
      {
        "strikePrice": 3900,
        "expiryDate": "31-Jul-2025",
        "PE": {
          "strikePrice": 3900,
          "expiryDate": "31-Jul-2025",
          "underlying": "SUPREMEIND",
          "identifier": "OPTSTKSUPREMEIND31-07-2025PE3900.00",
          "openInterest": 22,
          "changeinOpenInterest": 5,
          "pchangeinOpenInterest": 29.41176470588235,
          "totalTradedVolume": 28,
          "impliedVolatility": 35.28,
          "lastPrice": 18,
          "change": -23.65,
          "pChange": -56.78271308523409,
          "totalBuyQuantity": 21700,
          "totalSellQuantity": 6475,
          "bidQty": 175,
          "bidprice": 18.6,
          "askQty": 175,
          "askPrice": 31.8,
          "underlyingValue": 4232.1
        },
        "CE": {
          "strikePrice": 3900,
          "expiryDate": "31-Jul-2025",
          "underlying": "SUPREMEIND",
          "identifier": "OPTSTKSUPREMEIND31-07-2025CE3900.00",
          "openInterest": 3,
          "changeinOpenInterest": 0,
          "pchangeinOpenInterest": 0,
          "totalTradedVolume": 0,
          "impliedVolatility": 0,
          "lastPrice": 535,
          "change": 0,
          "pChange": 0,
          "totalBuyQuantity": 8400,
          "totalSellQuantity": 9450,
          "bidQty": 700,
          "bidprice": 356,
          "askQty": 700,
          "askPrice": 405.5,
          "underlyingValue": 4232.1
        }
      },
      {
        "strikePrice": 3950,
        "expiryDate": "31-Jul-2025",
        "PE": {
          "strikePrice": 3950,
          "expiryDate": "31-Jul-2025",
          "underlying": "SUPREMEIND",
          "identifier": "OPTSTKSUPREMEIND31-07-2025PE3950.00",
          "openInterest": 14,
          "changeinOpenInterest": 4,
          "pchangeinOpenInterest": 40,
          "totalTradedVolume": 13,
          "impliedVolatility": 34.98,
          "lastPrice": 24.8,
          "change": -28.95,
          "pChange": -53.860465116279066,
          "totalBuyQuantity": 6300,
          "totalSellQuantity": 5775,
          "bidQty": 175,
          "bidprice": 7.2,
          "askQty": 175,
          "askPrice": 48.1,
          "underlyingValue": 4232.1
        }
      },
      {
        "strikePrice": 4000,
        "expiryDate": "31-Jul-2025",
        "CE": {
          "strikePrice": 4000,
          "expiryDate": "31-Jul-2025",
          "underlying": "SUPREMEIND",
          "identifier": "OPTSTKSUPREMEIND31-07-2025CE4000.00",
          "openInterest": 14,
          "changeinOpenInterest": 4,
          "pchangeinOpenInterest": 40,
          "totalTradedVolume": 11,
          "impliedVolatility": 39.78,
          "lastPrice": 296,
          "change": 98.9,
          "pChange": 50.177574835109084,
          "totalBuyQuantity": 11725,
          "totalSellQuantity": 11025,
          "bidQty": 525,
          "bidprice": 272.95,
          "askQty": 175,
          "askPrice": 298.55,
          "underlyingValue": 4232.1
        },
        "PE": {
          "strikePrice": 4000,
          "expiryDate": "31-Jul-2025",
          "underlying": "SUPREMEIND",
          "identifier": "OPTSTKSUPREMEIND31-07-2025PE4000.00",
          "openInterest": 153,
          "changeinOpenInterest": -14,
          "pchangeinOpenInterest": -8.383233532934131,
          "totalTradedVolume": 108,
          "impliedVolatility": 36.1,
          "lastPrice": 37,
          "change": -33.849999999999994,
          "pChange": -47.77699364855328,
          "totalBuyQuantity": 20475,
          "totalSellQuantity": 10850,
          "bidQty": 175,
          "bidprice": 32.4,
          "askQty": 175,
          "askPrice": 44.65,
          "underlyingValue": 4232.1
        }
      },
      {
        "strikePrice": 4100,
        "expiryDate": "31-Jul-2025",
        "CE": {
          "strikePrice": 4100,
          "expiryDate": "31-Jul-2025",
          "underlying": "SUPREMEIND",
          "identifier": "OPTSTKSUPREMEIND31-07-2025CE4100.00",
          "openInterest": 56,
          "changeinOpenInterest": -5,
          "pchangeinOpenInterest": -8.19672131147541,
          "totalTradedVolume": 112,
          "impliedVolatility": 35.99,
          "lastPrice": 214,
          "change": 73.65,
          "pChange": 52.4759529747061,
          "totalBuyQuantity": 8750,
          "totalSellQuantity": 13125,
          "bidQty": 175,
          "bidprice": 196,
          "askQty": 175,
          "askPrice": 216.35,
          "underlyingValue": 4232.1
        },
        "PE": {
          "strikePrice": 4100,
          "expiryDate": "31-Jul-2025",
          "underlying": "SUPREMEIND",
          "identifier": "OPTSTKSUPREMEIND31-07-2025PE4100.00",
          "openInterest": 98,
          "changeinOpenInterest": 37,
          "pchangeinOpenInterest": 60.65573770491803,
          "totalTradedVolume": 112,
          "impliedVolatility": 35.17,
          "lastPrice": 61.45,
          "change": -48.64999999999999,
          "pChange": -44.18710263396911,
          "totalBuyQuantity": 12775,
          "totalSellQuantity": 8225,
          "bidQty": 175,
          "bidprice": 52.45,
          "askQty": 175,
          "askPrice": 67.6,
          "underlyingValue": 4232.1
        }
      },
      {
        "strikePrice": 4150,
        "expiryDate": "31-Jul-2025",
        "PE": {
          "strikePrice": 4150,
          "expiryDate": "31-Jul-2025",
          "underlying": "SUPREMEIND",
          "identifier": "OPTSTKSUPREMEIND31-07-2025PE4150.00",
          "openInterest": 47,
          "changeinOpenInterest": 0,
          "pchangeinOpenInterest": 0,
          "totalTradedVolume": 25,
          "impliedVolatility": 34.87,
          "lastPrice": 78.15,
          "change": -72.04999999999998,
          "pChange": -47.969374167776294,
          "totalBuyQuantity": 5600,
          "totalSellQuantity": 6475,
          "bidQty": 175,
          "bidprice": 67.95,
          "askQty": 350,
          "askPrice": 89.95,
          "underlyingValue": 4232.1
        },
        "CE": {
          "strikePrice": 4150,
          "expiryDate": "31-Jul-2025",
          "underlying": "SUPREMEIND",
          "identifier": "OPTSTKSUPREMEIND31-07-2025CE4150.00",
          "openInterest": 9,
          "changeinOpenInterest": -7,
          "pchangeinOpenInterest": -43.75,
          "totalTradedVolume": 35,
          "impliedVolatility": 35.62,
          "lastPrice": 180.9,
          "change": 71.05000000000001,
          "pChange": 64.67910787437417,
          "totalBuyQuantity": 6300,
          "totalSellQuantity": 3500,
          "bidQty": 175,
          "bidprice": 155.05,
          "askQty": 175,
          "askPrice": 197.8,
          "underlyingValue": 4232.1
        }
      },
      {
        "strikePrice": 4200,
        "expiryDate": "31-Jul-2025",
        "PE": {
          "strikePrice": 4200,
          "expiryDate": "31-Jul-2025",
          "underlying": "SUPREMEIND",
          "identifier": "OPTSTKSUPREMEIND31-07-2025PE4200.00",
          "openInterest": 156,
          "changeinOpenInterest": -12,
          "pchangeinOpenInterest": -7.142857142857143,
          "totalTradedVolume": 225,
          "impliedVolatility": 34.78,
          "lastPrice": 98.6,
          "change": -71.4,
          "pChange": -42.00000000000001,
          "totalBuyQuantity": 15750,
          "totalSellQuantity": 16450,
          "bidQty": 175,
          "bidprice": 90.05,
          "askQty": 350,
          "askPrice": 101.5,
          "underlyingValue": 4232.1
        },
        "CE": {
          "strikePrice": 4200,
          "expiryDate": "31-Jul-2025",
          "underlying": "SUPREMEIND",
          "identifier": "OPTSTKSUPREMEIND31-07-2025CE4200.00",
          "openInterest": 170,
          "changeinOpenInterest": 25,
          "pchangeinOpenInterest": 17.24137931034483,
          "totalTradedVolume": 559,
          "impliedVolatility": 36.78,
          "lastPrice": 156,
          "change": 59.400000000000006,
          "pChange": 61.49068322981367,
          "totalBuyQuantity": 13650,
          "totalSellQuantity": 18025,
          "bidQty": 175,
          "bidprice": 150.05,
          "askQty": 175,
          "askPrice": 154.7,
          "underlyingValue": 4232.1
        }
      },
      {
        "strikePrice": 4250,
        "expiryDate": "31-Jul-2025",
        "PE": {
          "strikePrice": 4250,
          "expiryDate": "31-Jul-2025",
          "underlying": "SUPREMEIND",
          "identifier": "OPTSTKSUPREMEIND31-07-2025PE4250.00",
          "openInterest": 46,
          "changeinOpenInterest": 7,
          "pchangeinOpenInterest": 17.94871794871795,
          "totalTradedVolume": 28,
          "impliedVolatility": 34.8,
          "lastPrice": 122.65,
          "change": -89.4,
          "pChange": -42.15986795567083,
          "totalBuyQuantity": 11725,
          "totalSellQuantity": 2275,
          "bidQty": 175,
          "bidprice": 122.2,
          "askQty": 350,
          "askPrice": 137.95,
          "underlyingValue": 4232.1
        },
        "CE": {
          "strikePrice": 4250,
          "expiryDate": "31-Jul-2025",
          "underlying": "SUPREMEIND",
          "identifier": "OPTSTKSUPREMEIND31-07-2025CE4250.00",
          "openInterest": 64,
          "changeinOpenInterest": 16,
          "pchangeinOpenInterest": 33.333333333333336,
          "totalTradedVolume": 165,
          "impliedVolatility": 36.17,
          "lastPrice": 128.15,
          "change": 51.400000000000006,
          "pChange": 66.97068403908796,
          "totalBuyQuantity": 16800,
          "totalSellQuantity": 7000,
          "bidQty": 175,
          "bidprice": 128,
          "askQty": 350,
          "askPrice": 143.95,
          "underlyingValue": 4232.1
        }
      },
      {
        "strikePrice": 4300,
        "expiryDate": "31-Jul-2025",
        "PE": {
          "strikePrice": 4300,
          "expiryDate": "31-Jul-2025",
          "underlying": "SUPREMEIND",
          "identifier": "OPTSTKSUPREMEIND31-07-2025PE4300.00",
          "openInterest": 198,
          "changeinOpenInterest": -67,
          "pchangeinOpenInterest": -25.28301886792453,
          "totalTradedVolume": 131,
          "impliedVolatility": 34.36,
          "lastPrice": 148.25,
          "change": -76.80000000000001,
          "pChange": -34.125749833370364,
          "totalBuyQuantity": 10500,
          "totalSellQuantity": 10500,
          "bidQty": 175,
          "bidprice": 147.6,
          "askQty": 175,
          "askPrice": 161.1,
          "underlyingValue": 4232.1
        },
        "CE": {
          "strikePrice": 4300,
          "expiryDate": "31-Jul-2025",
          "underlying": "SUPREMEIND",
          "identifier": "OPTSTKSUPREMEIND31-07-2025CE4300.00",
          "openInterest": 294,
          "changeinOpenInterest": -55,
          "pchangeinOpenInterest": -15.759312320916905,
          "totalTradedVolume": 928,
          "impliedVolatility": 36.17,
          "lastPrice": 105.5,
          "change": 44.7,
          "pChange": 73.51973684210527,
          "totalBuyQuantity": 25200,
          "totalSellQuantity": 16450,
          "bidQty": 350,
          "bidprice": 104,
          "askQty": 175,
          "askPrice": 105.5,
          "underlyingValue": 4232.1
        }
      },
      {
        "strikePrice": 4350,
        "expiryDate": "31-Jul-2025",
        "CE": {
          "strikePrice": 4350,
          "expiryDate": "31-Jul-2025",
          "underlying": "SUPREMEIND",
          "identifier": "OPTSTKSUPREMEIND31-07-2025CE4350.00",
          "openInterest": 78,
          "changeinOpenInterest": 9,
          "pchangeinOpenInterest": 13.043478260869565,
          "totalTradedVolume": 41,
          "impliedVolatility": 35.63,
          "lastPrice": 84,
          "change": 37.35,
          "pChange": 80.06430868167203,
          "totalBuyQuantity": 21525,
          "totalSellQuantity": 16800,
          "bidQty": 175,
          "bidprice": 82.35,
          "askQty": 175,
          "askPrice": 85,
          "underlyingValue": 4232.1
        },
        "PE": {
          "strikePrice": 4350,
          "expiryDate": "31-Jul-2025",
          "underlying": "SUPREMEIND",
          "identifier": "OPTSTKSUPREMEIND31-07-2025PE4350.00",
          "openInterest": 61,
          "changeinOpenInterest": 1,
          "pchangeinOpenInterest": 1.6666666666666667,
          "totalTradedVolume": 3,
          "impliedVolatility": 38.52,
          "lastPrice": 192.75,
          "change": -75.80000000000001,
          "pChange": -28.225656302364555,
          "totalBuyQuantity": 5950,
          "totalSellQuantity": 12600,
          "bidQty": 175,
          "bidprice": 167.2,
          "askQty": 175,
          "askPrice": 187.5,
          "underlyingValue": 4232.1
        }
      },
      {
        "strikePrice": 4400,
        "expiryDate": "31-Jul-2025",
        "CE": {
          "strikePrice": 4400,
          "expiryDate": "31-Jul-2025",
          "underlying": "SUPREMEIND",
          "identifier": "OPTSTKSUPREMEIND31-07-2025CE4400.00",
          "openInterest": 416,
          "changeinOpenInterest": 16,
          "pchangeinOpenInterest": 4,
          "totalTradedVolume": 293,
          "impliedVolatility": 35.23,
          "lastPrice": 66,
          "change": 28.85,
          "pChange": 77.65814266487214,
          "totalBuyQuantity": 27125,
          "totalSellQuantity": 15750,
          "bidQty": 175,
          "bidprice": 65.65,
          "askQty": 175,
          "askPrice": 67.8,
          "underlyingValue": 4232.1
        },
        "PE": {
          "strikePrice": 4400,
          "expiryDate": "31-Jul-2025",
          "underlying": "SUPREMEIND",
          "identifier": "OPTSTKSUPREMEIND31-07-2025PE4400.00",
          "openInterest": 117,
          "changeinOpenInterest": 0,
          "pchangeinOpenInterest": 0,
          "totalTradedVolume": 3,
          "impliedVolatility": 34.31,
          "lastPrice": 211.7,
          "change": -95.90000000000003,
          "pChange": -31.17685305591678,
          "totalBuyQuantity": 5250,
          "totalSellQuantity": 12600,
          "bidQty": 175,
          "bidprice": 202.15,
          "askQty": 175,
          "askPrice": 215,
          "underlyingValue": 4232.1
        }
      },
      {
        "strikePrice": 4450,
        "expiryDate": "31-Jul-2025",
        "PE": {
          "strikePrice": 4450,
          "expiryDate": "31-Jul-2025",
          "underlying": "SUPREMEIND",
          "identifier": "OPTSTKSUPREMEIND31-07-2025PE4450.00",
          "openInterest": 32,
          "changeinOpenInterest": 0,
          "pchangeinOpenInterest": 0,
          "totalTradedVolume": 0,
          "impliedVolatility": 0,
          "lastPrice": 274.95,
          "change": 0,
          "pChange": 0,
          "totalBuyQuantity": 5250,
          "totalSellQuantity": 10850,
          "bidQty": 525,
          "bidprice": 219.05,
          "askQty": 700,
          "askPrice": 274.2,
          "underlyingValue": 4232.1
        },
        "CE": {
          "strikePrice": 4450,
          "expiryDate": "31-Jul-2025",
          "underlying": "SUPREMEIND",
          "identifier": "OPTSTKSUPREMEIND31-07-2025CE4450.00",
          "openInterest": 29,
          "changeinOpenInterest": 0,
          "pchangeinOpenInterest": 0,
          "totalTradedVolume": 3,
          "impliedVolatility": 34.11,
          "lastPrice": 48.7,
          "change": 18.050000000000004,
          "pChange": 58.890701468189256,
          "totalBuyQuantity": 15575,
          "totalSellQuantity": 8225,
          "bidQty": 175,
          "bidprice": 48.8,
          "askQty": 700,
          "askPrice": 83.4,
          "underlyingValue": 4232.1
        }
      },
      {
        "strikePrice": 4500,
        "expiryDate": "31-Jul-2025",
        "CE": {
          "strikePrice": 4500,
          "expiryDate": "31-Jul-2025",
          "underlying": "SUPREMEIND",
          "identifier": "OPTSTKSUPREMEIND31-07-2025CE4500.00",
          "openInterest": 408,
          "changeinOpenInterest": -38,
          "pchangeinOpenInterest": -8.52017937219731,
          "totalTradedVolume": 581,
          "impliedVolatility": 35.46,
          "lastPrice": 41.1,
          "change": 18.150000000000002,
          "pChange": 79.08496732026144,
          "totalBuyQuantity": 29225,
          "totalSellQuantity": 19425,
          "bidQty": 175,
          "bidprice": 38.05,
          "askQty": 350,
          "askPrice": 41.75,
          "underlyingValue": 4232.1
        },
        "PE": {
          "strikePrice": 4500,
          "expiryDate": "31-Jul-2025",
          "underlying": "SUPREMEIND",
          "identifier": "OPTSTKSUPREMEIND31-07-2025PE4500.00",
          "openInterest": 162,
          "changeinOpenInterest": -1,
          "pchangeinOpenInterest": -0.6134969325153374,
          "totalTradedVolume": 2,
          "impliedVolatility": 34.63,
          "lastPrice": 287.1,
          "change": -120.75,
          "pChange": -29.60647296800294,
          "totalBuyQuantity": 6300,
          "totalSellQuantity": 13475,
          "bidQty": 350,
          "bidprice": 272.45,
          "askQty": 175,
          "askPrice": 300.5,
          "underlyingValue": 4232.1
        }
      },
      {
        "strikePrice": 4550,
        "expiryDate": "31-Jul-2025",
        "PE": {
          "strikePrice": 4550,
          "expiryDate": "31-Jul-2025",
          "underlying": "SUPREMEIND",
          "identifier": "OPTSTKSUPREMEIND31-07-2025PE4550.00",
          "openInterest": 14,
          "changeinOpenInterest": 0,
          "pchangeinOpenInterest": 0,
          "totalTradedVolume": 0,
          "impliedVolatility": 0,
          "lastPrice": 415.65,
          "change": 0,
          "pChange": 0,
          "totalBuyQuantity": 9975,
          "totalSellQuantity": 11375,
          "bidQty": 525,
          "bidprice": 298.05,
          "askQty": 525,
          "askPrice": 355.45,
          "underlyingValue": 4232.1
        },
        "CE": {
          "strikePrice": 4550,
          "expiryDate": "31-Jul-2025",
          "underlying": "SUPREMEIND",
          "identifier": "OPTSTKSUPREMEIND31-07-2025CE4550.00",
          "openInterest": 25,
          "changeinOpenInterest": -6,
          "pchangeinOpenInterest": -19.35483870967742,
          "totalTradedVolume": 16,
          "impliedVolatility": 35.56,
          "lastPrice": 31.9,
          "change": 16.9,
          "pChange": 112.66666666666664,
          "totalBuyQuantity": 21000,
          "totalSellQuantity": 7525,
          "bidQty": 175,
          "bidprice": 17.8,
          "askQty": 175,
          "askPrice": 45.35,
          "underlyingValue": 4232.1
        }
      },
      {
        "strikePrice": 4600,
        "expiryDate": "31-Jul-2025",
        "CE": {
          "strikePrice": 4600,
          "expiryDate": "31-Jul-2025",
          "underlying": "SUPREMEIND",
          "identifier": "OPTSTKSUPREMEIND31-07-2025CE4600.00",
          "openInterest": 214,
          "changeinOpenInterest": 7,
          "pchangeinOpenInterest": 3.3816425120772946,
          "totalTradedVolume": 145,
          "impliedVolatility": 36.04,
          "lastPrice": 25.3,
          "change": 11.100000000000001,
          "pChange": 78.16901408450705,
          "totalBuyQuantity": 23975,
          "totalSellQuantity": 12600,
          "bidQty": 1050,
          "bidprice": 24.45,
          "askQty": 175,
          "askPrice": 26.35,
          "underlyingValue": 4232.1
        },
        "PE": {
          "strikePrice": 4600,
          "expiryDate": "31-Jul-2025",
          "underlying": "SUPREMEIND",
          "identifier": "OPTSTKSUPREMEIND31-07-2025PE4600.00",
          "openInterest": 36,
          "changeinOpenInterest": 0,
          "pchangeinOpenInterest": 0,
          "totalTradedVolume": 0,
          "impliedVolatility": 0,
          "lastPrice": 367.85,
          "change": 0,
          "pChange": 0,
          "totalBuyQuantity": 7700,
          "totalSellQuantity": 10325,
          "bidQty": 700,
          "bidprice": 339.35,
          "askQty": 700,
          "askPrice": 382.2,
          "underlyingValue": 4232.1
        }
      },
      {
        "strikePrice": 4650,
        "expiryDate": "31-Jul-2025",
        "CE": {
          "strikePrice": 4650,
          "expiryDate": "31-Jul-2025",
          "underlying": "SUPREMEIND",
          "identifier": "OPTSTKSUPREMEIND31-07-2025CE4650.00",
          "openInterest": 46,
          "changeinOpenInterest": 7,
          "pchangeinOpenInterest": 17.94871794871795,
          "totalTradedVolume": 38,
          "impliedVolatility": 36.63,
          "lastPrice": 20.2,
          "change": 9.85,
          "pChange": 95.16908212560386,
          "totalBuyQuantity": 26950,
          "totalSellQuantity": 14525,
          "bidQty": 175,
          "bidprice": 7.1,
          "askQty": 175,
          "askPrice": 30.8,
          "underlyingValue": 4232.1
        },
        "PE": {
          "strikePrice": 4650,
          "expiryDate": "31-Jul-2025",
          "underlying": "SUPREMEIND",
          "identifier": "OPTSTKSUPREMEIND31-07-2025PE4650.00",
          "openInterest": 7,
          "changeinOpenInterest": 0,
          "pchangeinOpenInterest": 0,
          "totalTradedVolume": 0,
          "impliedVolatility": 0,
          "lastPrice": 330.65,
          "change": 0,
          "pChange": 0,
          "totalBuyQuantity": 9625,
          "totalSellQuantity": 5075,
          "bidQty": 175,
          "bidprice": 384.7,
          "askQty": 700,
          "askPrice": 435.6,
          "underlyingValue": 4232.1
        }
      },
      {
        "strikePrice": 4700,
        "expiryDate": "31-Jul-2025",
        "CE": {
          "strikePrice": 4700,
          "expiryDate": "31-Jul-2025",
          "underlying": "SUPREMEIND",
          "identifier": "OPTSTKSUPREMEIND31-07-2025CE4700.00",
          "openInterest": 137,
          "changeinOpenInterest": 8,
          "pchangeinOpenInterest": 6.2015503875969,
          "totalTradedVolume": 873,
          "impliedVolatility": 37.13,
          "lastPrice": 16,
          "change": 5.75,
          "pChange": 56.09756097560976,
          "totalBuyQuantity": 20475,
          "totalSellQuantity": 4375,
          "bidQty": 175,
          "bidprice": 15.55,
          "askQty": 525,
          "askPrice": 16.45,
          "underlyingValue": 4232.1
        },
        "PE": {
          "strikePrice": 4700,
          "expiryDate": "31-Jul-2025",
          "underlying": "SUPREMEIND",
          "identifier": "OPTSTKSUPREMEIND31-07-2025PE4700.00",
          "openInterest": 32,
          "changeinOpenInterest": 0,
          "pchangeinOpenInterest": 0,
          "totalTradedVolume": 0,
          "impliedVolatility": 0,
          "lastPrice": 450.05,
          "change": 0,
          "pChange": 0,
          "totalBuyQuantity": 9450,
          "totalSellQuantity": 10325,
          "bidQty": 1750,
          "bidprice": 426.2,
          "askQty": 700,
          "askPrice": 474.4,
          "underlyingValue": 4232.1
        }
      },
      {
        "strikePrice": 4750,
        "expiryDate": "31-Jul-2025",
        "CE": {
          "strikePrice": 4750,
          "expiryDate": "31-Jul-2025",
          "underlying": "SUPREMEIND",
          "identifier": "OPTSTKSUPREMEIND31-07-2025CE4750.00",
          "openInterest": 13,
          "changeinOpenInterest": 0,
          "pchangeinOpenInterest": 0,
          "totalTradedVolume": 0,
          "impliedVolatility": 0,
          "lastPrice": 62,
          "change": 0,
          "pChange": 0,
          "totalBuyQuantity": 10850,
          "totalSellQuantity": 0,
          "bidQty": 3500,
          "bidprice": 2.65,
          "askQty": 0,
          "askPrice": 0,
          "underlyingValue": 4232.1
        }
      },
      {
        "strikePrice": 4800,
        "expiryDate": "31-Jul-2025",
        "PE": {
          "strikePrice": 4800,
          "expiryDate": "31-Jul-2025",
          "underlying": "SUPREMEIND",
          "identifier": "OPTSTKSUPREMEIND31-07-2025PE4800.00",
          "openInterest": 2,
          "changeinOpenInterest": 0,
          "pchangeinOpenInterest": 0,
          "totalTradedVolume": 0,
          "impliedVolatility": 0,
          "lastPrice": 402.75,
          "change": 0,
          "pChange": 0,
          "totalBuyQuantity": 9450,
          "totalSellQuantity": 10325,
          "bidQty": 1750,
          "bidprice": 520.15,
          "askQty": 700,
          "askPrice": 568.95,
          "underlyingValue": 4232.1
        },
        "CE": {
          "strikePrice": 4800,
          "expiryDate": "31-Jul-2025",
          "underlying": "SUPREMEIND",
          "identifier": "OPTSTKSUPREMEIND31-07-2025CE4800.00",
          "openInterest": 110,
          "changeinOpenInterest": 26,
          "pchangeinOpenInterest": 30.952380952380953,
          "totalTradedVolume": 51,
          "impliedVolatility": 37.53,
          "lastPrice": 9.3,
          "change": 2.200000000000001,
          "pChange": 30.985915492957762,
          "totalBuyQuantity": 25725,
          "totalSellQuantity": 8050,
          "bidQty": 175,
          "bidprice": 6.55,
          "askQty": 175,
          "askPrice": 14.95,
          "underlyingValue": 4232.1
        }
      },
      {
        "strikePrice": 4900,
        "expiryDate": "31-Jul-2025",
        "CE": {
          "strikePrice": 4900,
          "expiryDate": "31-Jul-2025",
          "underlying": "SUPREMEIND",
          "identifier": "OPTSTKSUPREMEIND31-07-2025CE4900.00",
          "openInterest": 16,
          "changeinOpenInterest": -2,
          "pchangeinOpenInterest": -11.11111111111111,
          "totalTradedVolume": 3,
          "impliedVolatility": 40.44,
          "lastPrice": 7.4,
          "change": 1.3500000000000005,
          "pChange": 22.314049586776868,
          "totalBuyQuantity": 10325,
          "totalSellQuantity": 3150,
          "bidQty": 175,
          "bidprice": 1.7,
          "askQty": 175,
          "askPrice": 8.5,
          "underlyingValue": 4232.1
        }
      },
      {
        "strikePrice": 5000,
        "expiryDate": "31-Jul-2025",
        "PE": {
          "strikePrice": 5000,
          "expiryDate": "31-Jul-2025",
          "underlying": "SUPREMEIND",
          "identifier": "OPTSTKSUPREMEIND31-07-2025PE5000.00",
          "openInterest": 0,
          "changeinOpenInterest": 0,
          "pchangeinOpenInterest": 0,
          "totalTradedVolume": 0,
          "impliedVolatility": 0,
          "lastPrice": 0,
          "change": 0,
          "pChange": 0,
          "totalBuyQuantity": 9975,
          "totalSellQuantity": 10325,
          "bidQty": 525,
          "bidprice": 717.2,
          "askQty": 700,
          "askPrice": 766.75,
          "underlyingValue": 4232.1
        },
        "CE": {
          "strikePrice": 5000,
          "expiryDate": "31-Jul-2025",
          "underlying": "SUPREMEIND",
          "identifier": "OPTSTKSUPREMEIND31-07-2025CE5000.00",
          "openInterest": 300,
          "changeinOpenInterest": 14,
          "pchangeinOpenInterest": 4.895104895104895,
          "totalTradedVolume": 40,
          "impliedVolatility": 42.81,
          "lastPrice": 5.7,
          "change": 1.7000000000000002,
          "pChange": 42.50000000000001,
          "totalBuyQuantity": 28875,
          "totalSellQuantity": 7525,
          "bidQty": 175,
          "bidprice": 5.1,
          "askQty": 175,
          "askPrice": 5.85,
          "underlyingValue": 4232.1
        }
      },
      {
        "strikePrice": 5150,
        "expiryDate": "31-Jul-2025",
        "CE": {
          "strikePrice": 5150,
          "expiryDate": "31-Jul-2025",
          "underlying": "SUPREMEIND",
          "identifier": "OPTSTKSUPREMEIND31-07-2025CE5150.00",
          "openInterest": 72,
          "changeinOpenInterest": 8,
          "pchangeinOpenInterest": 12.5,
          "totalTradedVolume": 14,
          "impliedVolatility": 46.31,
          "lastPrice": 4.05,
          "change": 1.5499999999999998,
          "pChange": 61.999999999999986,
          "totalBuyQuantity": 3675,
          "totalSellQuantity": 875,
          "bidQty": 175,
          "bidprice": 0.4,
          "askQty": 175,
          "askPrice": 4.05,
          "underlyingValue": 4232.1
        }
      },
      {
        "strikePrice": 5200,
        "expiryDate": "31-Jul-2025",
        "CE": {
          "strikePrice": 5200,
          "expiryDate": "31-Jul-2025",
          "underlying": "SUPREMEIND",
          "identifier": "OPTSTKSUPREMEIND31-07-2025CE5200.00",
          "openInterest": 75,
          "changeinOpenInterest": 0,
          "pchangeinOpenInterest": 0,
          "totalTradedVolume": 0,
          "impliedVolatility": 0,
          "lastPrice": 1.4,
          "change": 0,
          "pChange": 0,
          "totalBuyQuantity": 7525,
          "totalSellQuantity": 700,
          "bidQty": 350,
          "bidprice": 1.45,
          "askQty": 700,
          "askPrice": 20.15,
          "underlyingValue": 4232.1
        }
      }
    ],
    "CE": {
      "totOI": 2553,
      "totVol": 3908
    },
    "PE": {
      "totOI": 1371,
      "totVol": 829
    }
  }
}